Workbook

Sheet README
A1: Libya Water–Energy Nexus Model (2020–2050)
A3: Purpose
A4: A simple annual-timestep model that translates population, GDP and a 100-million-tree afforestation programme into sector water demand, allocates demand across three supplies (local groundwater, pipeline transfers from southern fossil aquifers via the Great Man-Made River, and seawater desalination), and computes the associated electricity demand.
A6: Country context
A7: Libya is one of the most water-stressed countries in the world. Agriculture accounts for ~83% of withdrawals, municipal ~12%, industrial ~5% (FAO AQUASTAT via UNICEF 2022). Total renewable water resources are ~105 m³/cap/yr; >90% of supply comes from non-renewable fossil groundwater. The Great Man-Made River (GMMR) conveys water ~1,000–2,000 km from the Nubian Sandstone Aquifer in the south to coastal demand centres. It is modelled here under "pipeline imports" and is assumed to DECLINE over the model horizon — reflecting aquifer drawdown (estimated depletion within ~60 yr per Lonergan / Columbia State of the Planet 2011), infrastructure damage (by 2019, 101 of 479 western wells dismantled, MEI 2024) and stalled Phase III/IV works.
A9: Model logic
A10: 1. Population: linear interpolation between UN WPP 2024 medium-variant 2020 (6.735M) and 2050 (9.261M).
A11: 2. GDP per capita: user-specified CAGR (default 2.5%/yr).
A12: 3. Sector demand:
A13: • Domestic = L/cap/day × Population × 365 (with efficiency trend)
A14: • Industrial = (m³ / $1000 GDP) × Total GDP (with efficiency trend)
A15: • Agricultural = L/cap/day × Population × 365 (with efficiency trend)
... A71: UPDATE v4 (April 2026): Recalibrated to Libya National Water Security Strategy — Situation Analysis report (MoP/UNDP/Hydroconseil, Aug 2025). Demand intensities calibrated to hit reported 2025 figures (municipal 836, agricultural 6,098, industrial mid-465 Mm³/y). Added Surface water as a new supply source (~60 Mm³/y, declining). Capped desalination at the realistic ceiling implied by the report (70 → 750 Mm³/y by 2050, per Table 18 planned SWRO buildout). Added explicit 'Agriculture from groundwater (overdraft)' row to capture the unsustainable private-well withdrawals the report identifies as up to 5,900 Mm³/y (p.119). GW available baseline raised to 6,000 Mm³/y (was 3,500) to reflect total non-MMR groundwater incl. private wells. Both BAU and Conditional scenarios preserved; all charts and cross-references intact.

Sheet Inputs
A1: Libya Water-Energy Model — Inputs & Assumptions
A3: Parameter | B3: Value | C3: Units | D3: Source / Note
A5: DEMOGRAPHICS & ECONOMY
A6: Population 2020 | B6: 6735277 | C6: persons | D6: UN WPP 2024 medium variant | E6: *
A7: Population 2050 | B7: 10506952 | C7: persons | D7: Matched to SISEPUEDE | E7: *
A8: GDP per capita 2020 | B8: 6357 | C8: USD (current) | D8: World Bank WDI 2020 (volatile) | E8: *
A9: GDP per capita CAGR | B9: 0.028 | C9: per year | D9: Matched to SISEPUEDE | E9: *
A11: WATER DEMAND INTENSITIES
A12: Domestic water use 2020 | B12: 319 | C12: L/cap/day | D12: Calibrated to report (p.115): municipal demand 836 Mm³/y in 2025
A13: Domestic efficiency trend | B13: -0.005 | C13: per year | D13: Assumption: leak reduction, metering
A14: Industrial water intensity 2020 | B14: 9.1 | C14: m³ per $1000 GDP | D14: Calibrated to report (p.117): industrial demand 273-656 Mm³/y in 2025; midpoint ~465
A15: Industrial efficiency trend | B15: -0.01 | C15: per year | D15: Assumption: process efficiency
A16: Agricultural water use 2020 | B16: 2386 | C16: L/cap/day | D16: Calibrated to report (p.111, Table 26): agricultural demand 6,098 Mm³/y in 2025
A17: Agricultural efficiency trend | B17: -0.008 | C17: per year | D17: Assumption: irrigation modernization
A18: Surface water decline rate | B18: -0.01 | C18: per year | D18: Report p.61-69: rising evap & climate change
A19: SUPPLY CAPACITY & TRENDS
A20: Local groundwater yield 2020 | B20: 6000 | C20: M m³/yr | D20: Report p.119: ~5,900 Mm³/y from private wells + GCWW wells; mostly unsustainable. Excl. MMR.
A21: Groundwater decline rate | B21: -0.015 | C21: per year | D21: Overdraft & coastal salinization
A22: GMMR pipeline delivery 2020 | B22: 912 | C22: M m³/yr | D22: 2.5 Mm³/day × 365 (MEI 2024) | E22: Great Man Made River
A23: GMMR decline rate | B23: -0.02 | C23: per year | D23: Aquifer depletion (Lonergan ~60 yr) + infra decay
A24: Surface water 2020 | B24: 60 | C24: M m³/yr | D24: Report p.24-25: very limited; few small dams; high evap (1,700-6,000 mm/y)
A25: ENERGY INTENSITIES
A26: EI local groundwater 2020 | B26: =0.7*0.5 -> 0.35 | C26: kWh/m³ | D26: USGS/Denver 1.2-1.8 deep; 0.7 shallow/coastal We assumed that the majoriry of private-farm groundwater runs on diesel gensets and is not billed through the grid, given that FAO/World Bank water-sector assessments for the countrt, we can assume that private-farm pumping is largely unmetered and off-grid (approx 50%). Thus the energy intensity of this is scaled to what it is actually being demanded by the electricity grid.
A27: EI groundwater rise rate | B27: 0.015 | C27: per year | D27: Water-table drawdown raises lift
A28: EI pipeline (GMMR) 2020 | B28: 1.8 | C28: kWh/m³ | D28: Deep-well (500 m) + long conveyance; lit. 1.5-2.0 | E28: Note: check if this should chnage as a function of altitude
A29: EI pipeline rise rate | B29: 0.01 | C29: per year | D29: Rising lift as Nubian aquifer draws down
A30: EI desalination 2020 | B30: 3.5 | C30: kWh/m³ | D30: SWRO with ERDs (IRENA; ScienceDirect)
A31: EI desalination 2050 | B31: 3 | C31: kWh/m³ | D31: Efficiency gains toward 2.8 state-of-art
A32: Desalination capacity 2020 | B32: 20 | C32: M m³/yr | D32: Report p.92: 70-76 Mm³/y in 2010-2013
A33: 100-MILLION TREE AFFORESTATION PROGRAMME
A34: Programme start year | B34: 2026 | C34: year | D34: Assumption — edit to shift timeline
A35: Planting ramp (years) | B35: 10 | C35: years | D35: Linear planting of target over this period
A36: Target trees | B36: 100000000 | C36: trees | D36: Programme ambition (100 million)
A37: Water per tree | B37: 15 | C37: L/tree/day | D37: Drip-irrigated drought-tolerant; Becker et al. 2022; USU ext. ~41 L/d for mature arid shade tree | G37: =+B36*B37 -> 1500000000 | H37: L/day | I37: =+G37*365/1000 -> 547500000 | J37: m3/year | K37: =+I37/1000000 -> 547.5 | L37: Mm3/year
A38: Desalination capacity 2050 | B38: 750 | C38: M m³/yr | D38: Report p.92, Table 18: existing rehab + 14-15 planned SWRO at 2 Mm³/d ≈ 850 max; conservative 750
A39: RECYCLED WATER & ALLOCATION
A40: Parameter | B40: Value | C40: Units | D40: Source / Note
A41: Urban wastewater recovery share 2020 | B41: 0.01 | C41: share of urban water demand met | D41: Assumption: recoverable municipal wastewater
A42: Urban wastewater recovery share 2050 | B42: =0.35*0.1 -> 0.035 | C42: share of urban water demand met | D42: Assumption: better sewerage, treatment, and reuse
A43: Recycled water split to trees 2020 | B43: 0.5 | C43: share of recycled water | D43: Allocation priority from recycled water
A44: Recycled water split to trees 2050 | B44: 0.3 | C44: share of recycled water | D44: Less tree priority over time as ag reuse scales
A45: EI recycled water 2020 | B45: 0.8 | C45: kWh/m³ | D45: Assumption: treatment + pumping for non-potable reuse
A46: EI recycled water 2050 | B46: 0.65 | C46: kWh/m³ | D46: Efficiency improvement assumption
A48: EDITABLE ALLOCATION SHARES
A49: Parameter | B49: Value | C49: Units | D49: Source / Note
A50: Recycled water split to trees 2020 | B50: 0.5 | C50: share of recycled water | D50: Editable share; remainder goes to agriculture
A51: Recycled water split to trees 2050 | B51: 0.3 | C51: share of recycled water | D51: Editable share; remainder goes to agriculture
A52: Urban priority GW share | B52: 1 | C52: share of urban demand | D52: Default strict priority
A53: Urban priority GMMR share | B53: 1 | C53: share of urban residual | D53: Default strict priority
A54: Industrial priority GW share | B54: 1 | C54: share of industrial demand | D54: Default strict priority
A55: Industrial priority GMMR share | B55: 1 | C55: share of industrial residual | D55: Default strict priority
A56: Agriculture priority GW share | B56: 1 | C56: share of ag residual demand | D56: Default strict priority
A57: Agriculture priority GMMR share | B57: 1 | C57: share of ag residual after GW | D57: Default strict priority
A59: ADJUSTMENT FACTORS (v2 — technical review)
A60: Groundwater grid-electrified share | B60: 0.53 | C60: share (0-1) | D60: FAO/WB: ~47% private-farm pumping unmetered/off-grid (diesel). 0.53 is metered share
A61: Thermal desal fleet share 2020 | B61: 0.95 | C61: share | D61: README: Libya legacy fleet ~95% thermal (MSF/MED); Fadiel et al. 2025
A62: Thermal desal fleet share 2050 | B62: 0.1 | C62: share | D62: Assumption: new SWRO turnover dominates by 2050
A63: EI thermal desal (electric-equiv) | B63: 15 | C63: kWh-eq/m³ | D63: Midpoint of 15-25 kWh-eq/m³ literature range for MSF/MED
A64: GWh → PJ conversion factor | B64: 0.0036 | C64: PJ/GWh | D64: 3600 × 1e-6 = 3.6e-3. Used in Energy rows 17, 19-21, 32
A65: Libya total electricity generation (ref) | B65: 35000 | C65: GWh/yr | D65: IEA/OEC ~35 TWh (2021). Reference for Energy cross-check
A67: CONDITIONAL SCENARIO — TREATED WASTEWATER
A68: Parameter | B68: Value | C68: Units
A69: Urban wastewater recovery share 2020 — Conditional | B69: 0.01 | C69: share of urban water demand met | D69: Same as BAU 2020 (=Inputs!B41); only Conditional 2050 differs
A70: Urban wastewater recovery share 2050 — Conditional | B70: 0.35 | C70: share of urban water demand met
A71: Recycled water split to trees 2020 — Conditional | B71: 0.5 | C71: share of recycled water
A72: Recycled water split to trees 2050 — Conditional | B72: 0.6 | C72: share of recycled water

Sheet Demand
A1: Water Demand Projections — Libya (2020–2050)
A3: Metric | B3: Units | C3: Notes | D3: 2020 | E3: 2021 | F3: 2022 | G3: 2023 | H3: 2024 | I3: 2025 | J3: 2026 | K3: 2027 | L3: 2028 | M3: 2029 | N3: 2030 | O3: 2031 | P3: 2032 | Q3: 2033 | R3: 2034 | S3: 2035 | T3: 2036 | U3: 2037 | V3: 2038 | W3: 2039 | X3: 2040 | Y3: 2041 | Z3: 2042 | AA3: 2043 | AB3: 2044 | AC3: 2045 | AD3: 2046 | AE3: 2047 | AF3: 2048 | AG3: 2049 | AH3: 2050
A5: Population | B5: persons | C5: Linear interp UN WPP 2024 (2020 ↔ 2050) | D5: =Inputs!$B$6+(Inputs!$B$7-Inputs!$B$6)*(D$3-2020)/30 -> 6735277 | E5: =Inputs!$B$6+(Inputs!$B$7-Inputs!$B$6)*(E$3-2020)/30 -> 6860999.5 | F5: =Inputs!$B$6+(Inputs!$B$7-Inputs!$B$6)*(F$3-2020)/30 -> 6986722 | G5: =Inputs!$B$6+(Inputs!$B$7-Inputs!$B$6)*(G$3-2020)/30 -> 7112444.5 | H5: =Inputs!$B$6+(Inputs!$B$7-Inputs!$B$6)*(H$3-2020)/30 -> 7238167 | I5: =Inputs!$B$6+(Inputs!$B$7-Inputs!$B$6)*(I$3-2020)/30 -> 7363889.5 | J5: =Inputs!$B$6+(Inputs!$B$7-Inputs!$B$6)*(J$3-2020)/30 -> 7489612 | K5: =Inputs!$B$6+(Inputs!$B$7-Inputs!$B$6)*(K$3-2020)/30 -> 7615334.5 | ... AH5: =Inputs!$B$6+(Inputs!$B$7-Inputs!$B$6)*(AH$3-2020)/30 -> 10506952
A6: GDP per capita | B6: USD | C6: GDP_pc_2020 × (1+CAGR)^(year-2020) | D6: =Inputs!$B$8*(1+Inputs!$B$9)^(D$3-2020) -> 6357 | E6: =Inputs!$B$8*(1+Inputs!$B$9)^(E$3-2020) -> 6534.996 | F6: =Inputs!$B$8*(1+Inputs!$B$9)^(F$3-2020) -> 6717.9759 | G6: =Inputs!$B$8*(1+Inputs!$B$9)^(G$3-2020) -> 6906.0792 | H6: =Inputs!$B$8*(1+Inputs!$B$9)^(H$3-2020) -> 7099.4494 | I6: =Inputs!$B$8*(1+Inputs!$B$9)^(I$3-2020) -> 7298.234 | J6: =Inputs!$B$8*(1+Inputs!$B$9)^(J$3-2020) -> 7502.5846 | K6: =Inputs!$B$8*(1+Inputs!$B$9)^(K$3-2020) -> 7712.6569 | ... AH6: =Inputs!$B$8*(1+Inputs!$B$9)^(AH$3-2020) -> 14556.121
A7: Total GDP | B7: M USD | C7: Population × GDP per capita / 1e6 | D7: =D5*D6/1000000 -> 42816.156 | E7: =E5*E6/1000000 -> 44836.604 | F7: =F5*F6/1000000 -> 46936.63 | G7: =G5*G6/1000000 -> 49119.105 | H7: =H5*H6/1000000 -> 51387.001 | I7: =I5*I6/1000000 -> 53743.389 | J7: =J5*J6/1000000 -> 56191.447 | K7: =K5*K6/1000000 -> 58734.462 | ... AH7: =AH5*AH6/1000000 -> 152940.46
A9: Domestic intensity | B9: L/cap/day | C9: Base × (1+eff)^(year-2020) | D9: =Inputs!$B$12*(1+Inputs!$B$13)^(D$3-2020) -> 319 | E9: =Inputs!$B$12*(1+Inputs!$B$13)^(E$3-2020) -> 317.405 | F9: =Inputs!$B$12*(1+Inputs!$B$13)^(F$3-2020) -> 315.81797 | G9: =Inputs!$B$12*(1+Inputs!$B$13)^(G$3-2020) -> 314.23889 | H9: =Inputs!$B$12*(1+Inputs!$B$13)^(H$3-2020) -> 312.66769 | I9: =Inputs!$B$12*(1+Inputs!$B$13)^(I$3-2020) -> 311.10435 | J9: =Inputs!$B$12*(1+Inputs!$B$13)^(J$3-2020) -> 309.54883 | K9: =Inputs!$B$12*(1+Inputs!$B$13)^(K$3-2020) -> 308.00109 | ... AH9: =Inputs!$B$12*(1+Inputs!$B$13)^(AH$3-2020) -> 274.46256
A10: Industrial intensity | B10: m³/$1000 GDP | C10: Base × (1+eff)^(year-2020) | D10: =Inputs!$B$14*(1+Inputs!$B$15)^(D$3-2020) -> 9.1 | E10: =Inputs!$B$14*(1+Inputs!$B$15)^(E$3-2020) -> 9.009 | F10: =Inputs!$B$14*(1+Inputs!$B$15)^(F$3-2020) -> 8.91891 | G10: =Inputs!$B$14*(1+Inputs!$B$15)^(G$3-2020) -> 8.8297209 | H10: =Inputs!$B$14*(1+Inputs!$B$15)^(H$3-2020) -> 8.7414237 | I10: =Inputs!$B$14*(1+Inputs!$B$15)^(I$3-2020) -> 8.6540095 | J10: =Inputs!$B$14*(1+Inputs!$B$15)^(J$3-2020) -> 8.5674694 | K10: =Inputs!$B$14*(1+Inputs!$B$15)^(K$3-2020) -> 8.4817947 | ... AH10: =Inputs!$B$14*(1+Inputs!$B$15)^(AH$3-2020) -> 6.7312734
A11: Agricultural intensity | B11: L/cap/day | C11: Base × (1+eff)^(year-2020) | D11: =Inputs!$B$16*(1+Inputs!$B$17)^(D$3-2020) -> 2386 | E11: =Inputs!$B$16*(1+Inputs!$B$17)^(E$3-2020) -> 2366.912 | F11: =Inputs!$B$16*(1+Inputs!$B$17)^(F$3-2020) -> 2347.9767 | G11: =Inputs!$B$16*(1+Inputs!$B$17)^(G$3-2020) -> 2329.1929 | H11: =Inputs!$B$16*(1+Inputs!$B$17)^(H$3-2020) -> 2310.5593 | I11: =Inputs!$B$16*(1+Inputs!$B$17)^(I$3-2020) -> 2292.0749 | J11: =Inputs!$B$16*(1+Inputs!$B$17)^(J$3-2020) -> 2273.7383 | K11: =Inputs!$B$16*(1+Inputs!$B$17)^(K$3-2020) -> 2255.5484 | ... AH11: =Inputs!$B$16*(1+Inputs!$B$17)^(AH$3-2020) -> 1875.0835
A13: Domestic demand | B13: M m³/yr | C13: Pop × lpcd × 365 / 1e9 | D13: =D5*D9*365/1000000000 -> 784.22198 | E13: =E5*E9*365/1000000000 -> 794.86617 | F13: =F5*F9*365/1000000000 -> 805.38432 | G13: =G5*G9*365/1000000000 -> 815.77742 | H13: =H5*H9*365/1000000000 -> 826.04645 | I13: =I5*I9*365/1000000000 -> 836.1924 | J13: =J5*J9*365/1000000000 -> 846.21623 | K13: =K5*K9*365/1000000000 -> 856.11892 | ... AH13: =AH5*AH9*365/1000000000 -> 1052.5742
A14: Industrial demand | B14: M m³/yr | C14: GDP(M USD) × (m³/$1000) / 1000 | D14: =D7*D10/1000 -> 389.62702 | E14: =E7*E10/1000 -> 403.93297 | F14: =F7*F10/1000 -> 418.62358 | G14: =G7*G10/1000 -> 433.70799 | H14: =H7*H10/1000 -> 449.19554 | I14: =I7*I10/1000 -> 465.0958 | J14: =J7*J10/1000 -> 481.4185 | K14: =K7*K10/1000 -> 498.17365 | ... AH14: =AH7*AH10/1000 -> 1029.4841
A15: Agricultural demand | B15: M m³/yr | C15: Pop × lpcd × 365 / 1e9 | D15: =D5*D11*365/1000000000 -> 5865.6854 | E15: =E5*E11*365/1000000000 -> 5927.3744 | F15: =F5*F11*365/1000000000 -> 5987.7011 | G15: =G5*G11*365/1000000000 -> 6046.6831 | H15: =H5*H11*365/1000000000 -> 6104.3383 | I15: =I5*I11*365/1000000000 -> 6160.6839 | J15: =J5*J11*365/1000000000 -> 6215.7374 | K15: =K5*K11*365/1000000000 -> 6269.5157 | ... AH15: =AH5*AH11*365/1000000000 -> 7191.0154
A16: Active trees (100 M program) | B16: trees | C16: MIN(target, MAX(0, target×(year−start)/ramp)) | D16: =Inputs!$B$36*MIN(1,MAX(0,(D$3-Inputs!$B$34)/Inputs!$B$35)) -> 0 | E16: =Inputs!$B$36*MIN(1,MAX(0,(E$3-Inputs!$B$34)/Inputs!$B$35)) -> 0 | F16: =Inputs!$B$36*MIN(1,MAX(0,(F$3-Inputs!$B$34)/Inputs!$B$35)) -> 0 | G16: =Inputs!$B$36*MIN(1,MAX(0,(G$3-Inputs!$B$34)/Inputs!$B$35)) -> 0 | H16: =Inputs!$B$36*MIN(1,MAX(0,(H$3-Inputs!$B$34)/Inputs!$B$35)) -> 0 | I16: =Inputs!$B$36*MIN(1,MAX(0,(I$3-Inputs!$B$34)/Inputs!$B$35)) -> 0 | J16: =Inputs!$B$36*MIN(1,MAX(0,(J$3-Inputs!$B$34)/Inputs!$B$35)) -> 0 | K16: =Inputs!$B$36*MIN(1,MAX(0,(K$3-Inputs!$B$34)/Inputs!$B$35)) -> 10000000 | ... AH16: =Inputs!$B$36*MIN(1,MAX(0,(AH$3-Inputs!$B$34)/Inputs!$B$35)) -> 100000000
A17: Tree programme demand | B17: M m³/yr | C17: Active trees × L/tree/day × 365 / 1e9 | D17: =D16*Inputs!$B$37*365/1000000000 -> 0 | E17: =E16*Inputs!$B$37*365/1000000000 -> 0 | F17: =F16*Inputs!$B$37*365/1000000000 -> 0 | G17: =G16*Inputs!$B$37*365/1000000000 -> 0 | H17: =H16*Inputs!$B$37*365/1000000000 -> 0 | I17: =I16*Inputs!$B$37*365/1000000000 -> 0 | J17: =J16*Inputs!$B$37*365/1000000000 -> 0 | K17: =K16*Inputs!$B$37*365/1000000000 -> 54.75 | ... AH17: =AH16*Inputs!$B$37*365/1000000000 -> 547.5
A19: TOTAL water demand | B19: M m³/yr | C19: Sum of sectors + tree program | D19: =D13+D14+D15+D17 -> 7039.5344 | E19: =E13+E14+E15+E17 -> 7126.1736 | F19: =F13+F14+F15+F17 -> 7211.709 | G19: =G13+G14+G15+G17 -> 7296.1685 | H19: =H13+H14+H15+H17 -> 7379.5803 | I19: =I13+I14+I15+I17 -> 7461.9721 | J19: =J13+J14+J15+J17 -> 7543.3721 | K19: =K13+K14+K15+K17 -> 7678.5583 | ... AH19: =AH13+AH14+AH15+AH17 -> 9820.5736

Sheet Supply
A1: Water Supply Allocation — Libya (2020–2050)
A3: Metric | B3: Units | C3: Notes | D3: 2020 | E3: 2021 | F3: 2022 | G3: 2023 | H3: 2024 | I3: 2025 | J3: 2026 | K3: 2027 | L3: 2028 | M3: 2029 | N3: 2030 | O3: 2031 | P3: 2032 | Q3: 2033 | R3: 2034 | S3: 2035 | T3: 2036 | U3: 2037 | V3: 2038 | W3: 2039 | X3: 2040 | Y3: 2041 | Z3: 2042 | AA3: 2043 | AB3: 2044 | AC3: 2045 | AD3: 2046 | AE3: 2047 | AF3: 2048 | AG3: 2049 | AH3: 2050
A5: Total water demand | B5: M m³/yr | C5: link ← Demand row 19 | D5: =Demand!D19 -> 7039.5344 | E5: =Demand!E19 -> 7126.1736 | F5: =Demand!F19 -> 7211.709 | G5: =Demand!G19 -> 7296.1685 | H5: =Demand!H19 -> 7379.5803 | I5: =Demand!I19 -> 7461.9721 | J5: =Demand!J19 -> 7543.3721 | K5: =Demand!K19 -> 7678.5583 | ... AH5: =Demand!AH19 -> 9820.5736
A6: Of which tree programme | B6: M m³/yr | C6: link ← Demand row 17 | D6: =Demand!D17 -> 0 | E6: =Demand!E17 -> 0 | F6: =Demand!F17 -> 0 | G6: =Demand!G17 -> 0 | H6: =Demand!H17 -> 0 | I6: =Demand!I17 -> 0 | J6: =Demand!J17 -> 0 | K6: =Demand!K17 -> 54.75 | ... AH6: =Demand!AH17 -> 547.5
A7: Surface water to agriculture | B7: M m³/yr | C7: min(SW available, ag residual after recycled) | D7: =MIN(D11,MAX(D14-D17,0)) -> 60 | E7: =MIN(E11,MAX(E14-E17,0)) -> 59.4 | F7: =MIN(F11,MAX(F14-F17,0)) -> 58.806 | G7: =MIN(G11,MAX(G14-G17,0)) -> 58.21794 | H7: =MIN(H11,MAX(H14-H17,0)) -> 57.635761 | I7: =MIN(I11,MAX(I14-I17,0)) -> 57.059403 | J7: =MIN(J11,MAX(J14-J17,0)) -> 56.488809 | K7: =MIN(K11,MAX(K14-K17,0)) -> 55.923921 | ... AH7: =MIN(AH11,MAX(AH14-AH17,0)) -> 44.382022
A8: Local groundwater available | B8: M m³/yr | C8: GW_2020 × (1+decline)^(year-2020) | D8: =Inputs!$B$20*(1+Inputs!$B$21)^(D$3-2020) -> 6000 | E8: =Inputs!$B$20*(1+Inputs!$B$21)^(E$3-2020) -> 5910 | F8: =Inputs!$B$20*(1+Inputs!$B$21)^(F$3-2020) -> 5821.35 | G8: =Inputs!$B$20*(1+Inputs!$B$21)^(G$3-2020) -> 5734.0297 | H8: =Inputs!$B$20*(1+Inputs!$B$21)^(H$3-2020) -> 5648.0193 | I8: =Inputs!$B$20*(1+Inputs!$B$21)^(I$3-2020) -> 5563.299 | J8: =Inputs!$B$20*(1+Inputs!$B$21)^(J$3-2020) -> 5479.8495 | K8: =Inputs!$B$20*(1+Inputs!$B$21)^(K$3-2020) -> 5397.6518 | ... AH8: =Inputs!$B$20*(1+Inputs!$B$21)^(AH$3-2020) -> 3812.7486
A9: Pipeline (GMMR) available | B9: M m³/yr | C9: GMMR_2020 × (1+decline)^(year-2020) | D9: =Inputs!$B$22*(1+Inputs!$B$23)^(D$3-2020) -> 912 | E9: =Inputs!$B$22*(1+Inputs!$B$23)^(E$3-2020) -> 893.76 | F9: =Inputs!$B$22*(1+Inputs!$B$23)^(F$3-2020) -> 875.8848 | G9: =Inputs!$B$22*(1+Inputs!$B$23)^(G$3-2020) -> 858.3671 | H9: =Inputs!$B$22*(1+Inputs!$B$23)^(H$3-2020) -> 841.19976 | I9: =Inputs!$B$22*(1+Inputs!$B$23)^(I$3-2020) -> 824.37577 | J9: =Inputs!$B$22*(1+Inputs!$B$23)^(J$3-2020) -> 807.88825 | K9: =Inputs!$B$22*(1+Inputs!$B$23)^(K$3-2020) -> 791.73049 | ... AH9: =Inputs!$B$22*(1+Inputs!$B$23)^(AH$3-2020) -> 497.4817
A10: Groundwater + GMMR + Surface water | B10: M m³/yr | C10: GW + GMMR + SW | D10: =D8+D9+D11 -> 6972 | E10: =E8+E9+E11 -> 6863.16 | F10: =F8+F9+F11 -> 6756.0408 | G10: =G8+G9+G11 -> 6650.6148 | H10: =H8+H9+H11 -> 6546.8548 | I10: =I8+I9+I11 -> 6444.7342 | J10: =J8+J9+J11 -> 6344.2266 | K10: =K8+K9+K11 -> 6245.3062 | ... AH10: =AH8+AH9+AH11 -> 4354.6123
A11: Surface water available | B11: M m³/yr | C11: SW_2020 × (1+decline)^(year-2020) | D11: =Inputs!$B$24*(1+Inputs!$B$18)^(D$3-2020) -> 60 | E11: =Inputs!$B$24*(1+Inputs!$B$18)^(E$3-2020) -> 59.4 | F11: =Inputs!$B$24*(1+Inputs!$B$18)^(F$3-2020) -> 58.806 | G11: =Inputs!$B$24*(1+Inputs!$B$18)^(G$3-2020) -> 58.21794 | H11: =Inputs!$B$24*(1+Inputs!$B$18)^(H$3-2020) -> 57.635761 | I11: =Inputs!$B$24*(1+Inputs!$B$18)^(I$3-2020) -> 57.059403 | J11: =Inputs!$B$24*(1+Inputs!$B$18)^(J$3-2020) -> 56.488809 | K11: =Inputs!$B$24*(1+Inputs!$B$18)^(K$3-2020) -> 55.923921 | ... AH11: =Inputs!$B$24*(1+Inputs!$B$18)^(AH$3-2020) -> 44.382022
A12: Domestic demand | B12: M m³/yr | C12: link ← Demand domestic | D12: =Demand!D13 -> 784.22198 | E12: =Demand!E13 -> 794.86617 | F12: =Demand!F13 -> 805.38432 | G12: =Demand!G13 -> 815.77742 | H12: =Demand!H13 -> 826.04645 | I12: =Demand!I13 -> 836.1924 | J12: =Demand!J13 -> 846.21623 | K12: =Demand!K13 -> 856.11892 | ... AH12: =Demand!AH13 -> 1052.5742
A13: Industrial demand | B13: M m³/yr | C13: link ← Demand industrial | D13: =Demand!D14 -> 389.62702 | E13: =Demand!E14 -> 403.93297 | F13: =Demand!F14 -> 418.62358 | G13: =Demand!G14 -> 433.70799 | H13: =Demand!H14 -> 449.19554 | I13: =Demand!I14 -> 465.0958 | J13: =Demand!J14 -> 481.4185 | K13: =Demand!K14 -> 498.17365 | ... AH13: =Demand!AH14 -> 1029.4841
A14: Agricultural demand | B14: M m³/yr | C14: link ← Demand agriculture | D14: =Demand!D15 -> 5865.6854 | E14: =Demand!E15 -> 5927.3744 | F14: =Demand!F15 -> 5987.7011 | G14: =Demand!G15 -> 6046.6831 | H14: =Demand!H15 -> 6104.3383 | I14: =Demand!I15 -> 6160.6839 | J14: =Demand!J15 -> 6215.7374 | K14: =Demand!K15 -> 6269.5157 | ... AH14: =Demand!AH15 -> 7191.0154
A15: Recycled water available | B15: M m³/yr | C15: Urban demand met × recovery share | D15: =Demand!D13*(Inputs!B41+(Inputs!B42-Inputs!B41)*(D3-2020)/30) -> 7.8422198 | E15: =Demand!E13*(Inputs!B41+(Inputs!B42-Inputs!B41)*(E3-2020)/30) -> 8.6110502 | F15: =Demand!F13*(Inputs!B41+(Inputs!B42-Inputs!B41)*(F3-2020)/30) -> 9.3961504 | G15: =Demand!G13*(Inputs!B41+(Inputs!B42-Inputs!B41)*(G3-2020)/30) -> 10.197218 | H15: =Demand!H13*(Inputs!B41+(Inputs!B42-Inputs!B41)*(H3-2020)/30) -> 11.013953 | I15: =Demand!I13*(Inputs!B41+(Inputs!B42-Inputs!B41)*(I3-2020)/30) -> 11.846059 | J15: =Demand!J13*(Inputs!B41+(Inputs!B42-Inputs!B41)*(J3-2020)/30) -> 12.693243 | K15: =Demand!K13*(Inputs!B41+(Inputs!B42-Inputs!B41)*(K3-2020)/30) -> 13.555216 | L15: =Demand!L13*(Inputs!B41+(Inputs!B42-Inputs!B41)*(L3-2020)/30) -> 14.431691 | M15: =Demand!M13*(Inputs!B41+(Inputs!B42-Inputs!B41)*(M3-2020)/30) -> 15.322383 | N15: =Demand!N13*(Inputs!B41+(Inputs!B42-Inputs!B41)*(N3-2020)/30) -> 16.227011 | O15: =Demand!O13*(Inputs!B41+(Inputs!B42-Inputs!B41)*(O3-2020)/30) -> 17.1453 | P15: =Demand!P13*(Inputs!B41+(Inputs!B42-Inputs!B41)*(P3-2020)/30) -> 18.076973 | Q15: =Demand!Q13*(Inputs!B41+(Inputs!B42-Inputs!B41)*(Q3-2020)/30) -> 19.021759 | R15: =Demand!R13*(Inputs!B41+(Inputs!B42-Inputs!B41)*(R3-2020)/30) -> 19.979389 | S15: =Demand!S13*(Inputs!B41+(Inputs!B42-Inputs!B41)*(S3-2020)/30) -> 20.949598 | T15: =Demand!T13*(Inputs!B41+(Inputs!B42-Inputs!B41)*(T3-2020)/30) -> 21.932122 | U15: =Demand!U13*(Inputs!B41+(Inputs!B42-Inputs!B41)*(U3-2020)/30) -> 22.926702 | V15: =Demand!V13*(Inputs!B41+(Inputs!B42-Inputs!B41)*(V3-2020)/30) -> 23.933081 | W15: =Demand!W13*(Inputs!B41+(Inputs!B42-Inputs!B41)*(W3-2020)/30) -> 24.951004 | X15: =Demand!X13*(Inputs!B41+(Inputs!B42-Inputs!B41)*(X3-2020)/30) -> 25.980219 | Y15: =Demand!Y13*(Inputs!B41+(Inputs!B42-Inputs!B41)*(Y3-2020)/30) -> 27.020479 | Z15: =Demand!Z13*(Inputs!B41+(Inputs!B42-Inputs!B41)*(Z3-2020)/30) -> 28.071536 | AA15: =Demand!AA13*(Inputs!B41+(Inputs!B42-Inputs!B41)*(AA3-2020)/30) -> 29.133148 | AB15: =Demand!AB13*(Inputs!B41+(Inputs!B42-Inputs!B41)*(AB3-2020)/30) -> 30.205074 | AC15: =Demand!AC13*(Inputs!B41+(Inputs!B42-Inputs!B41)*(AC3-2020)/30) -> 31.287077 | AD15: =Demand!AD13*(Inputs!B41+(Inputs!B42-Inputs!B41)*(AD3-2020)/30) -> 32.378921 | AE15: =Demand!AE13*(Inputs!B41+(Inputs!B42-Inputs!B41)*(AE3-2020)/30) -> 33.480374 | AF15: =Demand!AF13*(Inputs!B41+(Inputs!B42-Inputs!B41)*(AF3-2020)/30) -> 34.591205 | AG15: =Demand!AG13*(Inputs!B41+(Inputs!B42-Inputs!B41)*(AG3-2020)/30) -> 35.711188 | AH15: =Demand!AH13*(Inputs!B41+(Inputs!B42-Inputs!B41)*(AH3-2020)/30) -> 36.840097
A16: Recycled water to trees | B16: M m³/yr | C16: Allocated first from recycled water, capped by tree demand | D16: =MIN(Supply!D6,Supply!D15*(Inputs!B50+(Inputs!B51-Inputs!B50)*(D3-2020)/30)) -> 0 | E16: =MIN(Supply!E6,Supply!E15*(Inputs!B50+(Inputs!B51-Inputs!B50)*(E3-2020)/30)) -> 0 | F16: =MIN(Supply!F6,Supply!F15*(Inputs!B50+(Inputs!B51-Inputs!B50)*(F3-2020)/30)) -> 0 | G16: =MIN(Supply!G6,Supply!G15*(Inputs!B50+(Inputs!B51-Inputs!B50)*(G3-2020)/30)) -> 0 | H16: =MIN(Supply!H6,Supply!H15*(Inputs!B50+(Inputs!B51-Inputs!B50)*(H3-2020)/30)) -> 0 | I16: =MIN(Supply!I6,Supply!I15*(Inputs!B50+(Inputs!B51-Inputs!B50)*(I3-2020)/30)) -> 0 | J16: =MIN(Supply!J6,Supply!J15*(Inputs!B50+(Inputs!B51-Inputs!B50)*(J3-2020)/30)) -> 0 | K16: =MIN(Supply!K6,Supply!K15*(Inputs!B50+(Inputs!B51-Inputs!B50)*(K3-2020)/30)) -> 6.1450314 | L16: =MIN(Supply!L6,Supply!L15*(Inputs!B50+(Inputs!B51-Inputs!B50)*(L3-2020)/30)) -> 6.4461551 | M16: =MIN(Supply!M6,Supply!M15*(Inputs!B50+(Inputs!B51-Inputs!B50)*(M3-2020)/30)) -> 6.7418483 | N16: =MIN(Supply!N6,Supply!N15*(Inputs!B50+(Inputs!B51-Inputs!B50)*(N3-2020)/30)) -> 7.031705 | O16: =MIN(Supply!O6,Supply!O15*(Inputs!B50+(Inputs!B51-Inputs!B50)*(O3-2020)/30)) -> 7.3153279 | P16: =MIN(Supply!P6,Supply!P15*(Inputs!B50+(Inputs!B51-Inputs!B50)*(P3-2020)/30)) -> 7.5923286 | Q16: =MIN(Supply!Q6,Supply!Q15*(Inputs!B50+(Inputs!B51-Inputs!B50)*(Q3-2020)/30)) -> 7.8623269 | R16: =MIN(Supply!R6,Supply!R15*(Inputs!B50+(Inputs!B51-Inputs!B50)*(R3-2020)/30)) -> 8.1249515 | S16: =MIN(Supply!S6,Supply!S15*(Inputs!B50+(Inputs!B51-Inputs!B50)*(S3-2020)/30)) -> 8.3798391 | T16: =MIN(Supply!T6,Supply!T15*(Inputs!B50+(Inputs!B51-Inputs!B50)*(T3-2020)/30)) -> 8.6266348 | U16: =MIN(Supply!U6,Supply!U15*(Inputs!B50+(Inputs!B51-Inputs!B50)*(U3-2020)/30)) -> 8.8649916 | V16: =MIN(Supply!V6,Supply!V15*(Inputs!B50+(Inputs!B51-Inputs!B50)*(V3-2020)/30)) -> 9.0945707 | W16: =MIN(Supply!W6,Supply!W15*(Inputs!B50+(Inputs!B51-Inputs!B50)*(W3-2020)/30)) -> 9.3150414 | X16: =MIN(Supply!X6,Supply!X15*(Inputs!B50+(Inputs!B51-Inputs!B50)*(X3-2020)/30)) -> 9.5260803 | Y16: =MIN(Supply!Y6,Supply!Y15*(Inputs!B50+(Inputs!B51-Inputs!B50)*(Y3-2020)/30)) -> 9.7273723 | Z16: =MIN(Supply!Z6,Supply!Z15*(Inputs!B50+(Inputs!B51-Inputs!B50)*(Z3-2020)/30)) -> 9.9186094 | AA16: =MIN(Supply!AA6,Supply!AA15*(Inputs!B50+(Inputs!B51-Inputs!B50)*(AA3-2020)/30)) -> 10.099491 | AB16: =MIN(Supply!AB6,Supply!AB15*(Inputs!B50+(Inputs!B51-Inputs!B50)*(AB3-2020)/30)) -> 10.269725 | AC16: =MIN(Supply!AC6,Supply!AC15*(Inputs!B50+(Inputs!B51-Inputs!B50)*(AC3-2020)/30)) -> 10.429026 | AD16: =MIN(Supply!AD6,Supply!AD15*(Inputs!B50+(Inputs!B51-Inputs!B50)*(AD3-2020)/30)) -> 10.577114 | AE16: =MIN(Supply!AE6,Supply!AE15*(Inputs!B50+(Inputs!B51-Inputs!B50)*(AE3-2020)/30)) -> 10.71372 | AF16: =MIN(Supply!AF6,Supply!AF15*(Inputs!B50+(Inputs!B51-Inputs!B50)*(AF3-2020)/30)) -> 10.838578 | AG16: =MIN(Supply!AG6,Supply!AG15*(Inputs!B50+(Inputs!B51-Inputs!B50)*(AG3-2020)/30)) -> 10.951431 | AH16: =MIN(Supply!AH6,Supply!AH15*(Inputs!B50+(Inputs!B51-Inputs!B50)*(AH3-2020)/30)) -> 11.052029
A17: Recycled water to agriculture | B17: M m³/yr | C17: Residual recycled water after trees | D17: =MIN(Supply!D14,MAX(Supply!D15-Supply!D16,0)) -> 7.8422198 | E17: =MIN(Supply!E14,MAX(Supply!E15-Supply!E16,0)) -> 8.6110502 | F17: =MIN(Supply!F14,MAX(Supply!F15-Supply!F16,0)) -> 9.3961504 | G17: =MIN(Supply!G14,MAX(Supply!G15-Supply!G16,0)) -> 10.197218 | H17: =MIN(Supply!H14,MAX(Supply!H15-Supply!H16,0)) -> 11.013953 | I17: =MIN(Supply!I14,MAX(Supply!I15-Supply!I16,0)) -> 11.846059 | J17: =MIN(Supply!J14,MAX(Supply!J15-Supply!J16,0)) -> 12.693243 | K17: =MIN(Supply!K14,MAX(Supply!K15-Supply!K16,0)) -> 7.4101849 | ... AH17: =MIN(Supply!AH14,MAX(Supply!AH15-Supply!AH16,0)) -> 25.788068
A18: Urban from groundwater | B18: M m³/yr | C18: Urban first draw on GW | D18: =MIN(Supply!D12*Inputs!B52,Supply!D8) -> 784.22198 | E18: =MIN(Supply!E12*Inputs!B52,Supply!E8) -> 794.86617 | F18: =MIN(Supply!F12*Inputs!B52,Supply!F8) -> 805.38432 | G18: =MIN(Supply!G12*Inputs!B52,Supply!G8) -> 815.77742 | H18: =MIN(Supply!H12*Inputs!B52,Supply!H8) -> 826.04645 | I18: =MIN(Supply!I12*Inputs!B52,Supply!I8) -> 836.1924 | J18: =MIN(Supply!J12*Inputs!B52,Supply!J8) -> 846.21623 | K18: =MIN(Supply!K12*Inputs!B52,Supply!K8) -> 856.11892 | L18: =MIN(Supply!L12*Inputs!B52,Supply!L8) -> 865.90143 | M18: =MIN(Supply!M12*Inputs!B52,Supply!M8) -> 875.56472 | N18: =MIN(Supply!N12*Inputs!B52,Supply!N8) -> 885.10972 | O18: =MIN(Supply!O12*Inputs!B52,Supply!O8) -> 894.53738 | P18: =MIN(Supply!P12*Inputs!B52,Supply!P8) -> 903.84864 | Q18: =MIN(Supply!Q12*Inputs!B52,Supply!Q8) -> 913.04442 | R18: =MIN(Supply!R12*Inputs!B52,Supply!R8) -> 922.12565 | S18: =MIN(Supply!S12*Inputs!B52,Supply!S8) -> 931.09324 | T18: =MIN(Supply!T12*Inputs!B52,Supply!T8) -> 939.9481 | U18: =MIN(Supply!U12*Inputs!B52,Supply!U8) -> 948.69113 | V18: =MIN(Supply!V12*Inputs!B52,Supply!V8) -> 957.32324 | W18: =MIN(Supply!W12*Inputs!B52,Supply!W8) -> 965.8453 | X18: =MIN(Supply!X12*Inputs!B52,Supply!X8) -> 974.25822 | Y18: =MIN(Supply!Y12*Inputs!B52,Supply!Y8) -> 982.56286 | Z18: =MIN(Supply!Z12*Inputs!B52,Supply!Z8) -> 990.76009 | AA18: =MIN(Supply!AA12*Inputs!B52,Supply!AA8) -> 998.85079 | AB18: =MIN(Supply!AB12*Inputs!B52,Supply!AB8) -> 1006.8358 | AC18: =MIN(Supply!AC12*Inputs!B52,Supply!AC8) -> 1014.716 | AD18: =MIN(Supply!AD12*Inputs!B52,Supply!AD8) -> 1022.4922 | AE18: =MIN(Supply!AE12*Inputs!B52,Supply!AE8) -> 1030.1653 | AF18: =MIN(Supply!AF12*Inputs!B52,Supply!AF8) -> 1037.7361 | AG18: =MIN(Supply!AG12*Inputs!B52,Supply!AG8) -> 1045.2055 | AH18: =MIN(Supply!AH12*Inputs!B52,Supply!AH8) -> 1052.5742
A19: Urban from GMMR | B19: M m³/yr | C19: Urban then GMMR | D19: =MIN(MAX(Supply!D12-D18,0)*Inputs!B53,MAX(Supply!D9,0)) -> 0 | E19: =MIN(MAX(Supply!E12-E18,0)*Inputs!B53,MAX(Supply!E9,0)) -> 0 | F19: =MIN(MAX(Supply!F12-F18,0)*Inputs!B53,MAX(Supply!F9,0)) -> 0 | G19: =MIN(MAX(Supply!G12-G18,0)*Inputs!B53,MAX(Supply!G9,0)) -> 0 | H19: =MIN(MAX(Supply!H12-H18,0)*Inputs!B53,MAX(Supply!H9,0)) -> 0 | I19: =MIN(MAX(Supply!I12-I18,0)*Inputs!B53,MAX(Supply!I9,0)) -> 0 | J19: =MIN(MAX(Supply!J12-J18,0)*Inputs!B53,MAX(Supply!J9,0)) -> 0 | K19: =MIN(MAX(Supply!K12-K18,0)*Inputs!B53,MAX(Supply!K9,0)) -> 0 | L19: =MIN(MAX(Supply!L12-L18,0)*Inputs!B53,MAX(Supply!L9,0)) -> 0 | M19: =MIN(MAX(Supply!M12-M18,0)*Inputs!B53,MAX(Supply!M9,0)) -> 0 | N19: =MIN(MAX(Supply!N12-N18,0)*Inputs!B53,MAX(Supply!N9,0)) -> 0 | O19: =MIN(MAX(Supply!O12-O18,0)*Inputs!B53,MAX(Supply!O9,0)) -> 0 | P19: =MIN(MAX(Supply!P12-P18,0)*Inputs!B53,MAX(Supply!P9,0)) -> 0 | Q19: =MIN(MAX(Supply!Q12-Q18,0)*Inputs!B53,MAX(Supply!Q9,0)) -> 0 | R19: =MIN(MAX(Supply!R12-R18,0)*Inputs!B53,MAX(Supply!R9,0)) -> 0 | S19: =MIN(MAX(Supply!S12-S18,0)*Inputs!B53,MAX(Supply!S9,0)) -> 0 | T19: =MIN(MAX(Supply!T12-T18,0)*Inputs!B53,MAX(Supply!T9,0)) -> 0 | U19: =MIN(MAX(Supply!U12-U18,0)*Inputs!B53,MAX(Supply!U9,0)) -> 0 | V19: =MIN(MAX(Supply!V12-V18,0)*Inputs!B53,MAX(Supply!V9,0)) -> 0 | W19: =MIN(MAX(Supply!W12-W18,0)*Inputs!B53,MAX(Supply!W9,0)) -> 0 | X19: =MIN(MAX(Supply!X12-X18,0)*Inputs!B53,MAX(Supply!X9,0)) -> 0 | Y19: =MIN(MAX(Supply!Y12-Y18,0)*Inputs!B53,MAX(Supply!Y9,0)) -> 0 | Z19: =MIN(MAX(Supply!Z12-Z18,0)*Inputs!B53,MAX(Supply!Z9,0)) -> 0 | AA19: =MIN(MAX(Supply!AA12-AA18,0)*Inputs!B53,MAX(Supply!AA9,0)) -> 0 | AB19: =MIN(MAX(Supply!AB12-AB18,0)*Inputs!B53,MAX(Supply!AB9,0)) -> 0 | AC19: =MIN(MAX(Supply!AC12-AC18,0)*Inputs!B53,MAX(Supply!AC9,0)) -> 0 | AD19: =MIN(MAX(Supply!AD12-AD18,0)*Inputs!B53,MAX(Supply!AD9,0)) -> 0 | AE19: =MIN(MAX(Supply!AE12-AE18,0)*Inputs!B53,MAX(Supply!AE9,0)) -> 0 | AF19: =MIN(MAX(Supply!AF12-AF18,0)*Inputs!B53,MAX(Supply!AF9,0)) -> 0 | AG19: =MIN(MAX(Supply!AG12-AG18,0)*Inputs!B53,MAX(Supply!AG9,0)) -> 0 | AH19: =MIN(MAX(Supply!AH12-AH18,0)*Inputs!B53,MAX(Supply!AH9,0)) -> 0
A20: Urban from desalination | B20: M m³/yr | C20: Urban residual desal | D20: =MAX(Supply!D12-D18-D19,0) -> 0 | E20: =MAX(Supply!E12-E18-E19,0) -> 0 | F20: =MAX(Supply!F12-F18-F19,0) -> 0 | G20: =MAX(Supply!G12-G18-G19,0) -> 0 | H20: =MAX(Supply!H12-H18-H19,0) -> 0 | I20: =MAX(Supply!I12-I18-I19,0) -> 0 | J20: =MAX(Supply!J12-J18-J19,0) -> 0 | K20: =MAX(Supply!K12-K18-K19,0) -> 0 | ... AH20: =MAX(Supply!AH12-AH18-AH19,0) -> 0
A21: Industrial from groundwater | B21: M m³/yr | C21: Industrial second draw on GW | D21: =MIN(Supply!D13*Inputs!B54,MAX(Supply!D8-D18,0)) -> 389.62702 | E21: =MIN(Supply!E13*Inputs!B54,MAX(Supply!E8-E18,0)) -> 403.93297 | F21: =MIN(Supply!F13*Inputs!B54,MAX(Supply!F8-F18,0)) -> 418.62358 | G21: =MIN(Supply!G13*Inputs!B54,MAX(Supply!G8-G18,0)) -> 433.70799 | H21: =MIN(Supply!H13*Inputs!B54,MAX(Supply!H8-H18,0)) -> 449.19554 | I21: =MIN(Supply!I13*Inputs!B54,MAX(Supply!I8-I18,0)) -> 465.0958 | J21: =MIN(Supply!J13*Inputs!B54,MAX(Supply!J8-J18,0)) -> 481.4185 | K21: =MIN(Supply!K13*Inputs!B54,MAX(Supply!K8-K18,0)) -> 498.17365 | L21: =MIN(Supply!L13*Inputs!B54,MAX(Supply!L8-L18,0)) -> 515.37143 | M21: =MIN(Supply!M13*Inputs!B54,MAX(Supply!M8-M18,0)) -> 533.02228 | N21: =MIN(Supply!N13*Inputs!B54,MAX(Supply!N8-N18,0)) -> 551.13685 | O21: =MIN(Supply!O13*Inputs!B54,MAX(Supply!O8-O18,0)) -> 569.72603 | P21: =MIN(Supply!P13*Inputs!B54,MAX(Supply!P8-P18,0)) -> 588.80096 | Q21: =MIN(Supply!Q13*Inputs!B54,MAX(Supply!Q8-Q18,0)) -> 608.373 | R21: =MIN(Supply!R13*Inputs!B54,MAX(Supply!R8-R18,0)) -> 628.4538 | S21: =MIN(Supply!S13*Inputs!B54,MAX(Supply!S8-S18,0)) -> 649.05523 | T21: =MIN(Supply!T13*Inputs!B54,MAX(Supply!T8-T18,0)) -> 670.18945 | U21: =MIN(Supply!U13*Inputs!B54,MAX(Supply!U8-U18,0)) -> 691.86886 | V21: =MIN(Supply!V13*Inputs!B54,MAX(Supply!V8-V18,0)) -> 714.10614 | W21: =MIN(Supply!W13*Inputs!B54,MAX(Supply!W8-W18,0)) -> 736.91428 | X21: =MIN(Supply!X13*Inputs!B54,MAX(Supply!X8-X18,0)) -> 760.3065 | Y21: =MIN(Supply!Y13*Inputs!B54,MAX(Supply!Y8-Y18,0)) -> 784.29636 | Z21: =MIN(Supply!Z13*Inputs!B54,MAX(Supply!Z8-Z18,0)) -> 808.89768 | AA21: =MIN(Supply!AA13*Inputs!B54,MAX(Supply!AA8-AA18,0)) -> 834.1246 | AB21: =MIN(Supply!AB13*Inputs!B54,MAX(Supply!AB8-AB18,0)) -> 859.99157 | AC21: =MIN(Supply!AC13*Inputs!B54,MAX(Supply!AC8-AC18,0)) -> 886.51336 | AD21: =MIN(Supply!AD13*Inputs!B54,MAX(Supply!AD8-AD18,0)) -> 913.70504 | AE21: =MIN(Supply!AE13*Inputs!B54,MAX(Supply!AE8-AE18,0)) -> 941.58203 | AF21: =MIN(Supply!AF13*Inputs!B54,MAX(Supply!AF8-AF18,0)) -> 970.16008 | AG21: =MIN(Supply!AG13*Inputs!B54,MAX(Supply!AG8-AG18,0)) -> 999.45527 | AH21: =MIN(Supply!AH13*Inputs!B54,MAX(Supply!AH8-AH18,0)) -> 1029.4841
A22: Industrial from GMMR | B22: M m³/yr | C22: Industrial then GMMR | D22: =MIN(MAX(Supply!D13-D21,0)*Inputs!B55,MAX(Supply!D9-D19,0)) -> 0 | E22: =MIN(MAX(Supply!E13-E21,0)*Inputs!B55,MAX(Supply!E9-E19,0)) -> 0 | F22: =MIN(MAX(Supply!F13-F21,0)*Inputs!B55,MAX(Supply!F9-F19,0)) -> 0 | G22: =MIN(MAX(Supply!G13-G21,0)*Inputs!B55,MAX(Supply!G9-G19,0)) -> 0 | H22: =MIN(MAX(Supply!H13-H21,0)*Inputs!B55,MAX(Supply!H9-H19,0)) -> 0 | I22: =MIN(MAX(Supply!I13-I21,0)*Inputs!B55,MAX(Supply!I9-I19,0)) -> 0 | J22: =MIN(MAX(Supply!J13-J21,0)*Inputs!B55,MAX(Supply!J9-J19,0)) -> 0 | K22: =MIN(MAX(Supply!K13-K21,0)*Inputs!B55,MAX(Supply!K9-K19,0)) -> 0 | L22: =MIN(MAX(Supply!L13-L21,0)*Inputs!B55,MAX(Supply!L9-L19,0)) -> 0 | M22: =MIN(MAX(Supply!M13-M21,0)*Inputs!B55,MAX(Supply!M9-M19,0)) -> 0 | N22: =MIN(MAX(Supply!N13-N21,0)*Inputs!B55,MAX(Supply!N9-N19,0)) -> 0 | O22: =MIN(MAX(Supply!O13-O21,0)*Inputs!B55,MAX(Supply!O9-O19,0)) -> 0 | P22: =MIN(MAX(Supply!P13-P21,0)*Inputs!B55,MAX(Supply!P9-P19,0)) -> 0 | Q22: =MIN(MAX(Supply!Q13-Q21,0)*Inputs!B55,MAX(Supply!Q9-Q19,0)) -> 0 | R22: =MIN(MAX(Supply!R13-R21,0)*Inputs!B55,MAX(Supply!R9-R19,0)) -> 0 | S22: =MIN(MAX(Supply!S13-S21,0)*Inputs!B55,MAX(Supply!S9-S19,0)) -> 0 | T22: =MIN(MAX(Supply!T13-T21,0)*Inputs!B55,MAX(Supply!T9-T19,0)) -> 0 | U22: =MIN(MAX(Supply!U13-U21,0)*Inputs!B55,MAX(Supply!U9-U19,0)) -> 0 | V22: =MIN(MAX(Supply!V13-V21,0)*Inputs!B55,MAX(Supply!V9-V19,0)) -> 0 | W22: =MIN(MAX(Supply!W13-W21,0)*Inputs!B55,MAX(Supply!W9-W19,0)) -> 0 | X22: =MIN(MAX(Supply!X13-X21,0)*Inputs!B55,MAX(Supply!X9-X19,0)) -> 0 | Y22: =MIN(MAX(Supply!Y13-Y21,0)*Inputs!B55,MAX(Supply!Y9-Y19,0)) -> 0 | Z22: =MIN(MAX(Supply!Z13-Z21,0)*Inputs!B55,MAX(Supply!Z9-Z19,0)) -> 0 | AA22: =MIN(MAX(Supply!AA13-AA21,0)*Inputs!B55,MAX(Supply!AA9-AA19,0)) -> 0 | AB22: =MIN(MAX(Supply!AB13-AB21,0)*Inputs!B55,MAX(Supply!AB9-AB19,0)) -> 0 | AC22: =MIN(MAX(Supply!AC13-AC21,0)*Inputs!B55,MAX(Supply!AC9-AC19,0)) -> 0 | AD22: =MIN(MAX(Supply!AD13-AD21,0)*Inputs!B55,MAX(Supply!AD9-AD19,0)) -> 0 | AE22: =MIN(MAX(Supply!AE13-AE21,0)*Inputs!B55,MAX(Supply!AE9-AE19,0)) -> 0 | AF22: =MIN(MAX(Supply!AF13-AF21,0)*Inputs!B55,MAX(Supply!AF9-AF19,0)) -> 0 | AG22: =MIN(MAX(Supply!AG13-AG21,0)*Inputs!B55,MAX(Supply!AG9-AG19,0)) -> 0 | AH22: =MIN(MAX(Supply!AH13-AH21,0)*Inputs!B55,MAX(Supply!AH9-AH19,0)) -> 0
A23: Industrial from desalination | B23: M m³/yr | C23: Industrial residual desal | D23: =MAX(Supply!D13-D21-D22,0) -> 0 | E23: =MAX(Supply!E13-E21-E22,0) -> 0 | F23: =MAX(Supply!F13-F21-F22,0) -> 0 | G23: =MAX(Supply!G13-G21-G22,0) -> 0 | H23: =MAX(Supply!H13-H21-H22,0) -> 0 | I23: =MAX(Supply!I13-I21-I22,0) -> 0 | J23: =MAX(Supply!J13-J21-J22,0) -> 0 | K23: =MAX(Supply!K13-K21-K22,0) -> 0 | ... AH23: =MAX(Supply!AH13-AH21-AH22,0) -> 0
A24: Agriculture from groundwater | B24: M m³/yr | C24: Agriculture draw on GW after recycled | D24: =MIN(MAX(D14-D17-D7,0)*Inputs!$B$56,MAX(D8-D18-D21,0)) -> 4826.151 | E24: =MIN(MAX(E14-E17-E7,0)*Inputs!$B$56,MAX(E8-E18-E21,0)) -> 4711.2009 | F24: =MIN(MAX(F14-F17-F7,0)*Inputs!$B$56,MAX(F8-F18-F21,0)) -> 4597.3421 | G24: =MIN(MAX(G14-G17-G7,0)*Inputs!$B$56,MAX(G8-G18-G21,0)) -> 4484.5443 | H24: =MIN(MAX(H14-H17-H7,0)*Inputs!$B$56,MAX(H8-H18-H21,0)) -> 4372.7773 | I24: =MIN(MAX(I14-I17-I7,0)*Inputs!$B$56,MAX(I8-I18-I21,0)) -> 4262.0108 | J24: =MIN(MAX(J14-J17-J7,0)*Inputs!$B$56,MAX(J8-J18-J21,0)) -> 4152.2148 | K24: =MIN(MAX(K14-K17-K7,0)*Inputs!$B$56,MAX(K8-K18-K21,0)) -> 4043.3592 | ... AH24: =MIN(MAX(AH14-AH17-AH7,0)*Inputs!$B$56,MAX(AH8-AH18-AH21,0)) -> 1730.6903
A25: Agriculture from GMMR | B25: M m³/yr | C25: Agriculture then GMMR | D25: =MIN(MAX(MAX(D14-D17-D7,0)-D24,0)*Inputs!$B$57,MAX(D9-D19-D22,0)) -> 912 | E25: =MIN(MAX(MAX(E14-E17-E7,0)-E24,0)*Inputs!$B$57,MAX(E9-E19-E22,0)) -> 893.76 | F25: =MIN(MAX(MAX(F14-F17-F7,0)-F24,0)*Inputs!$B$57,MAX(F9-F19-F22,0)) -> 875.8848 | G25: =MIN(MAX(MAX(G14-G17-G7,0)-G24,0)*Inputs!$B$57,MAX(G9-G19-G22,0)) -> 858.3671 | H25: =MIN(MAX(MAX(H14-H17-H7,0)-H24,0)*Inputs!$B$57,MAX(H9-H19-H22,0)) -> 841.19976 | I25: =MIN(MAX(MAX(I14-I17-I7,0)-I24,0)*Inputs!$B$57,MAX(I9-I19-I22,0)) -> 824.37577 | J25: =MIN(MAX(MAX(J14-J17-J7,0)-J24,0)*Inputs!$B$57,MAX(J9-J19-J22,0)) -> 807.88825 | K25: =MIN(MAX(MAX(K14-K17-K7,0)-K24,0)*Inputs!$B$57,MAX(K9-K19-K22,0)) -> 791.73049 | ... AH25: =MIN(MAX(MAX(AH14-AH17-AH7,0)-AH24,0)*Inputs!$B$57,MAX(AH9-AH19-AH22,0)) -> 497.4817
A26: Agriculture from desalination | B26: M m³/yr | C26: Agriculture residual desal | D26: 0 | E26: 0 | F26: 0 | G26: 0 | H26: 0 | I26: 0 | J26: 0 | K26: 0 | L26: 0 | M26: 0 | N26: 0 | O26: 0 | P26: 0 | Q26: 0 | R26: 0 | S26: 0 | T26: 0 | U26: 0 | V26: 0 | W26: 0 | X26: 0 | Y26: 0 | Z26: 0 | AA26: 0 | AB26: 0 | AC26: 0 | AD26: 0 | AE26: 0 | AF26: 0 | AG26: 0 | AH26: 0
A27: Trees from desalination | B27: M m³/yr | C27: Tree residual after recycled | D27: =MAX(Supply!D6-Supply!D16,0) -> 0 | E27: =MAX(Supply!E6-Supply!E16,0) -> 0 | F27: =MAX(Supply!F6-Supply!F16,0) -> 0 | G27: =MAX(Supply!G6-Supply!G16,0) -> 0 | H27: =MAX(Supply!H6-Supply!H16,0) -> 0 | I27: =MAX(Supply!I6-Supply!I16,0) -> 0 | J27: =MAX(Supply!J6-Supply!J16,0) -> 0 | K27: =MAX(Supply!K6-Supply!K16,0) -> 48.604969 | ... AH27: =MAX(Supply!AH6-Supply!AH16,0) -> 536.44797
A28: CHECK: allocated demand incl recycled | B28: M m³/yr | C28: Should equal total demand | D28: =D18+D19+D20+D21+D22+D23+D17+D24+D25+D26+D16+D27+D7+D39 -> 7039.5344 | E28: =E18+E19+E20+E21+E22+E23+E17+E24+E25+E26+E16+E27+E7+E39 -> 7126.1736 | F28: =F18+F19+F20+F21+F22+F23+F17+F24+F25+F26+F16+F27+F7+F39 -> 7211.709 | G28: =G18+G19+G20+G21+G22+G23+G17+G24+G25+G26+G16+G27+G7+G39 -> 7296.1685 | H28: =H18+H19+H20+H21+H22+H23+H17+H24+H25+H26+H16+H27+H7+H39 -> 7379.5803 | I28: =I18+I19+I20+I21+I22+I23+I17+I24+I25+I26+I16+I27+I7+I39 -> 7461.9721 | J28: =J18+J19+J20+J21+J22+J23+J17+J24+J25+J26+J16+J27+J7+J39 -> 7543.3721 | K28: =K18+K19+K20+K21+K22+K23+K17+K24+K25+K26+K16+K27+K7+K39 -> 7678.5583 | ... AH28: =AH18+AH19+AH20+AH21+AH22+AH23+AH17+AH24+AH25+AH26+AH16+AH27+AH7+AH39 -> 9820.5736
A29: Desalination required (total) | B29: M m³/yr | C29: MAX(0, Total demand − GW − GMMR) | D29: =D20+D23+D27 -> 0 | E29: =E20+E23+E27 -> 0 | F29: =F20+F23+F27 -> 0 | G29: =G20+G23+G27 -> 0 | H29: =H20+H23+H27 -> 0 | I29: =I20+I23+I27 -> 0 | J29: =J20+J23+J27 -> 0 | K29: =K20+K23+K27 -> 48.604969 | ... AH29: =AH20+AH23+AH27 -> 536.44797
A30: Desalination if NO tree programme | B30: M m³/yr | C30: MAX(0, (Demand−Tree) − GW − GMMR) | D30: =D20+D23 -> 0 | E30: =E20+E23 -> 0 | F30: =F20+F23 -> 0 | G30: =G20+G23 -> 0 | H30: =H20+H23 -> 0 | I30: =I20+I23 -> 0 | J30: =J20+J23 -> 0 | K30: =K20+K23 -> 0 | ... AH30: =AH20+AH23 -> 0
A31: Incremental desal for tree programme | B31: M m³/yr | C31: Row 12 − Row 13 | D31: =D29-D30 -> 0 | E31: =Supply!E29-Supply!E30 -> 0 | F31: =Supply!F29-Supply!F30 -> 0 | G31: =Supply!G29-Supply!G30 -> 0 | H31: =Supply!H29-Supply!H30 -> 0 | I31: =Supply!I29-Supply!I30 -> 0 | J31: =Supply!J29-Supply!J30 -> 0 | K31: =Supply!K29-Supply!K30 -> 48.604969 | L31: =Supply!L29-Supply!L30 -> 103.05384 | ... AH31: =Supply!AH29-Supply!AH30 -> 536.44797
A32: → equivalent SWRO capacity | B32: m³/day | C32: Row 14 × 1e6 / 365 | D32: =D31*1000000/365 -> 0 | E32: =Supply!E31*1000000/365 -> 0 | F32: =Supply!F31*1000000/365 -> 0 | G32: =Supply!G31*1000000/365 -> 0 | H32: =Supply!H31*1000000/365 -> 0 | I32: =Supply!I31*1000000/365 -> 0 | J32: =Supply!J31*1000000/365 -> 0 | K32: =Supply!K31*1000000/365 -> 133164.3 | L32: =Supply!L31*1000000/365 -> 282339.3 | ... AH32: =Supply!AH31*1000000/365 -> 1469720.5
A33: Desalination capacity (max) | B33: M m³/yr | C33: Linear from 2020 baseline to 2050 max (per report p.92) | D33: =Inputs!$B$32+(Inputs!$B$38-Inputs!$B$32)*(D$3-2020)/30 -> 20 | E33: =Inputs!$B$32+(Inputs!$B$38-Inputs!$B$32)*(E$3-2020)/30 -> 44.333333 | F33: =Inputs!$B$32+(Inputs!$B$38-Inputs!$B$32)*(F$3-2020)/30 -> 68.666667 | G33: =Inputs!$B$32+(Inputs!$B$38-Inputs!$B$32)*(G$3-2020)/30 -> 93 | H33: =Inputs!$B$32+(Inputs!$B$38-Inputs!$B$32)*(H$3-2020)/30 -> 117.33333 | I33: =Inputs!$B$32+(Inputs!$B$38-Inputs!$B$32)*(I$3-2020)/30 -> 141.66667 | J33: =Inputs!$B$32+(Inputs!$B$38-Inputs!$B$32)*(J$3-2020)/30 -> 166 | K33: =Inputs!$B$32+(Inputs!$B$38-Inputs!$B$32)*(K$3-2020)/30 -> 190.33333 | ... AH33: =Inputs!$B$32+(Inputs!$B$38-Inputs!$B$32)*(AH$3-2020)/30 -> 750
A34: Recycled water used (total) | B34: M m³/yr | C34: Recycled water to trees + agriculture | D34: =Supply!D16+Supply!D17 -> 7.8422198 | E34: =Supply!E16+Supply!E17 -> 8.6110502 | F34: =Supply!F16+Supply!F17 -> 9.3961504 | G34: =Supply!G16+Supply!G17 -> 10.197218 | H34: =Supply!H16+Supply!H17 -> 11.013953 | I34: =Supply!I16+Supply!I17 -> 11.846059 | J34: =Supply!J16+Supply!J17 -> 12.693243 | K34: =Supply!K16+Supply!K17 -> 13.555216 | ... AH34: =Supply!AH16+Supply!AH17 -> 36.840097
A35: Total water supply (incl. recycled) | B35: M m³/yr | C35: GW + GMMR + desal + recycled | D35: =D18+D21+D24+D39+D19+D22+D25+D7+D29+D34 -> 7039.5344 | E35: =E18+E21+E24+E39+E19+E22+E25+E7+E29+E34 -> 7126.1736 | F35: =F18+F21+F24+F39+F19+F22+F25+F7+F29+F34 -> 7211.709 | G35: =G18+G21+G24+G39+G19+G22+G25+G7+G29+G34 -> 7296.1685 | H35: =H18+H21+H24+H39+H19+H22+H25+H7+H29+H34 -> 7379.5803 | I35: =I18+I21+I24+I39+I19+I22+I25+I7+I29+I34 -> 7461.9721 | J35: =J18+J21+J24+J39+J19+J22+J25+J7+J29+J34 -> 7543.3721 | K35: =K18+K21+K24+K39+K19+K22+K25+K7+K29+K34 -> 7678.5583 | ... AH35: =AH18+AH21+AH24+AH39+AH19+AH22+AH25+AH7+AH29+AH34 -> 9820.5736
A36: Share: Local groundwater | B36: % | D36: =(D18+D21+D24+D39)/D5 -> 0.86080866 | E36: =(E18+E21+E24+E39)/E5 -> 0.86503682 | F36: =(F18+F21+F24+F39)/F5 -> 0.8690897 | G36: =(G18+G21+G24+G39)/G5 -> 0.87297686 | H36: =(H18+H21+H24+H39)/H5 -> 0.87670715 | I36: =(I18+I21+I24+I39)/I5 -> 0.88028885 | J36: =(J18+J21+J24+J39)/J5 -> 0.88372968 | K36: =(K18+K21+K24+K39)/K5 -> 0.88151232 | ... AH36: =(AH18+AH21+AH24+AH39)/AH5 -> 0.88644739
A37: Share: GMMR pipeline | B37: % | D37: =(D19+D22+D25)/D5 -> 0.12955402 | E37: =(E19+E22+E25)/E5 -> 0.12541934 | F37: =(F19+F22+F25)/F5 -> 0.12145315 | G37: =(G19+G22+G25)/G5 -> 0.11764628 | H37: =(H19+H22+H25)/H5 -> 0.11399019 | I37: =(I19+I22+I25)/I5 -> 0.11047693 | J37: =(J19+J22+J25)/J5 -> 0.10709909 | K37: =(K19+K22+K25)/K5 -> 0.10310926 | ... AH37: =(AH19+AH22+AH25)/AH5 -> 0.050657092
A38: Share: Desalination | B38: % | D38: =Supply!D29/Supply!D5 -> 0 | E38: =Supply!E29/Supply!E5 -> 0 | F38: =Supply!F29/Supply!F5 -> 0 | G38: =Supply!G29/Supply!G5 -> 0 | H38: =Supply!H29/Supply!H5 -> 0 | I38: =Supply!I29/Supply!I5 -> 0 | J38: =Supply!J29/Supply!J5 -> 0 | K38: =Supply!K29/Supply!K5 -> 0.0063299603 | ... AH38: =Supply!AH29/Supply!AH5 -> 0.054624912
A39: Ag from groundwater (overdraft) | B39: M m³/yr | C39: Residual ag demand absorbed by unsustainable private wells when desal hits cap | D39: =MAX(MAX(D14-D17-D7,0)-D24-D25,0) -> 59.692163 | E39: =MAX(MAX(E14-E17-E7,0)-E24-E25,0) -> 254.40254 | F39: =MAX(MAX(F14-F17-F7,0)-F24-F25,0) -> 446.27203 | G39: =MAX(MAX(G14-G17-G7,0)-G24-G25,0) -> 635.35653 | H39: =MAX(MAX(H14-H17-H7,0)-H24-H25,0) -> 821.71148 | I39: =MAX(MAX(I14-I17-I7,0)-I24-I25,0) -> 1005.3919 | J39: =MAX(MAX(J14-J17-J7,0)-J24-J25,0) -> 1186.4523 | K39: =MAX(MAX(K14-K17-K7,0)-K24-K25,0) -> 1371.0919 | ... AH39: =MAX(MAX(AH14-AH17-AH7,0)-AH24-AH25,0) -> 4892.6733
A40: CHECK: Supply − Demand | B40: M m³/yr | C40: Should equal zero | D40: =Supply!D35-Supply!D5 -> 0 | E40: =Supply!E35-Supply!E5 -> 0 | F40: =Supply!F35-Supply!F5 -> 0 | G40: =Supply!G35-Supply!G5 -> 0 | H40: =Supply!H35-Supply!H5 -> 0 | I40: =Supply!I35-Supply!I5 -> 0 | J40: =Supply!J35-Supply!J5 -> 0 | K40: =Supply!K35-Supply!K5 -> 0 | ... AH40: =Supply!AH35-Supply!AH5 -> 0
A41: Share: Surface water | B41: % | C41: Surface water used / total demand | D41: =D7/D5 -> 0.008523291 | E41: =E7/E5 -> 0.0083354691 | F41: =F7/F5 -> 0.0081542392 | G41: =G7/G5 -> 0.0079792482 | H41: =H7/H5 -> 0.0078101679 | I41: =I7/I5 -> 0.0076466921 | J41: =J7/J5 -> 0.0074885354 | K41: =K7/K5 -> 0.0072831278 | ... AH41: =AH7/AH5 -> 0.0045192902
A42: CONDITIONAL SCENARIO — higher treated wastewater recovery
A43: Recycled water available (Conditional) | B43: M m³/yr | C43: Urban demand × Conditional recovery share | D43: =Demand!D13*(Inputs!$B$69+(Inputs!$B$70-Inputs!$B$69)*(D$3-2020)/30) -> 7.8422198 | E43: =Demand!E13*(Inputs!$B$69+(Inputs!$B$70-Inputs!$B$69)*(E$3-2020)/30) -> 16.957145 | F43: =Demand!F13*(Inputs!$B$69+(Inputs!$B$70-Inputs!$B$69)*(F$3-2020)/30) -> 26.309221 | G43: =Demand!G13*(Inputs!$B$69+(Inputs!$B$70-Inputs!$B$69)*(G$3-2020)/30) -> 35.894206 | H43: =Demand!H13*(Inputs!$B$69+(Inputs!$B$70-Inputs!$B$69)*(H$3-2020)/30) -> 45.707904 | I43: =Demand!I13*(Inputs!$B$69+(Inputs!$B$70-Inputs!$B$69)*(I$3-2020)/30) -> 55.74616 | J43: =Demand!J13*(Inputs!$B$69+(Inputs!$B$70-Inputs!$B$69)*(J$3-2020)/30) -> 66.004866 | K43: =Demand!K13*(Inputs!$B$69+(Inputs!$B$70-Inputs!$B$69)*(K$3-2020)/30) -> 76.479957 | ... AH43: =Demand!AH13*(Inputs!$B$69+(Inputs!$B$70-Inputs!$B$69)*(AH$3-2020)/30) -> 368.40097
A44: Recycled water to trees (Conditional) | B44: M m³/yr | C44: Allocated first from recycled water, capped by tree demand | D44: =MIN(Supply!D6,Supply!D43*(Inputs!$B$71+(Inputs!$B$72-Inputs!$B$71)*(D$3-2020)/30)) -> 0 | E44: =MIN(Supply!E6,Supply!E43*(Inputs!$B$71+(Inputs!$B$72-Inputs!$B$71)*(E$3-2020)/30)) -> 0 | F44: =MIN(Supply!F6,Supply!F43*(Inputs!$B$71+(Inputs!$B$72-Inputs!$B$71)*(F$3-2020)/30)) -> 0 | G44: =MIN(Supply!G6,Supply!G43*(Inputs!$B$71+(Inputs!$B$72-Inputs!$B$71)*(G$3-2020)/30)) -> 0 | H44: =MIN(Supply!H6,Supply!H43*(Inputs!$B$71+(Inputs!$B$72-Inputs!$B$71)*(H$3-2020)/30)) -> 0 | I44: =MIN(Supply!I6,Supply!I43*(Inputs!$B$71+(Inputs!$B$72-Inputs!$B$71)*(I$3-2020)/30)) -> 0 | J44: =MIN(Supply!J6,Supply!J43*(Inputs!$B$71+(Inputs!$B$72-Inputs!$B$71)*(J$3-2020)/30)) -> 0 | K44: =MIN(Supply!K6,Supply!K43*(Inputs!$B$71+(Inputs!$B$72-Inputs!$B$71)*(K$3-2020)/30)) -> 40.024511 | ... AH44: =MIN(Supply!AH6,Supply!AH43*(Inputs!$B$71+(Inputs!$B$72-Inputs!$B$71)*(AH$3-2020)/30)) -> 221.04058
A45: Recycled water to agriculture (Conditional) | B45: M m³/yr | C45: Residual recycled water after trees | D45: =MIN(Supply!D14,MAX(Supply!D43-Supply!D44,0)) -> 7.8422198 | E45: =MIN(Supply!E14,MAX(Supply!E43-Supply!E44,0)) -> 16.957145 | F45: =MIN(Supply!F14,MAX(Supply!F43-Supply!F44,0)) -> 26.309221 | G45: =MIN(Supply!G14,MAX(Supply!G43-Supply!G44,0)) -> 35.894206 | H45: =MIN(Supply!H14,MAX(Supply!H43-Supply!H44,0)) -> 45.707904 | I45: =MIN(Supply!I14,MAX(Supply!I43-Supply!I44,0)) -> 55.74616 | J45: =MIN(Supply!J14,MAX(Supply!J43-Supply!J44,0)) -> 66.004866 | K45: =MIN(Supply!K14,MAX(Supply!K43-Supply!K44,0)) -> 36.455446 | ... AH45: =MIN(Supply!AH14,MAX(Supply!AH43-Supply!AH44,0)) -> 147.36039
A46: Urban from groundwater (Conditional) | B46: M m³/yr | C46: Urban first draw on GW | D46: =MIN(Supply!D12*Inputs!$B$52,Supply!D8) -> 784.22198 | E46: =MIN(Supply!E12*Inputs!$B$52,Supply!E8) -> 794.86617 | F46: =MIN(Supply!F12*Inputs!$B$52,Supply!F8) -> 805.38432 | G46: =MIN(Supply!G12*Inputs!$B$52,Supply!G8) -> 815.77742 | H46: =MIN(Supply!H12*Inputs!$B$52,Supply!H8) -> 826.04645 | I46: =MIN(Supply!I12*Inputs!$B$52,Supply!I8) -> 836.1924 | J46: =MIN(Supply!J12*Inputs!$B$52,Supply!J8) -> 846.21623 | K46: =MIN(Supply!K12*Inputs!$B$52,Supply!K8) -> 856.11892 | ... AH46: =MIN(Supply!AH12*Inputs!$B$52,Supply!AH8) -> 1052.5742
A47: Urban from GMMR (Conditional) | B47: M m³/yr | C47: Urban then GMMR | D47: =MIN(MAX(Supply!D12-D46,0)*Inputs!$B$53,MAX(Supply!D9,0)) -> 0 | E47: =MIN(MAX(Supply!E12-E46,0)*Inputs!$B$53,MAX(Supply!E9,0)) -> 0 | F47: =MIN(MAX(Supply!F12-F46,0)*Inputs!$B$53,MAX(Supply!F9,0)) -> 0 | G47: =MIN(MAX(Supply!G12-G46,0)*Inputs!$B$53,MAX(Supply!G9,0)) -> 0 | H47: =MIN(MAX(Supply!H12-H46,0)*Inputs!$B$53,MAX(Supply!H9,0)) -> 0 | I47: =MIN(MAX(Supply!I12-I46,0)*Inputs!$B$53,MAX(Supply!I9,0)) -> 0 | J47: =MIN(MAX(Supply!J12-J46,0)*Inputs!$B$53,MAX(Supply!J9,0)) -> 0 | K47: =MIN(MAX(Supply!K12-K46,0)*Inputs!$B$53,MAX(Supply!K9,0)) -> 0 | ... AH47: =MIN(MAX(Supply!AH12-AH46,0)*Inputs!$B$53,MAX(Supply!AH9,0)) -> 0
A48: Urban from desalination (Conditional) | B48: M m³/yr | C48: Urban residual desal | D48: =MAX(Supply!D12-D46-D47,0) -> 0 | E48: =MAX(Supply!E12-E46-E47,0) -> 0 | F48: =MAX(Supply!F12-F46-F47,0) -> 0 | G48: =MAX(Supply!G12-G46-G47,0) -> 0 | H48: =MAX(Supply!H12-H46-H47,0) -> 0 | I48: =MAX(Supply!I12-I46-I47,0) -> 0 | J48: =MAX(Supply!J12-J46-J47,0) -> 0 | K48: =MAX(Supply!K12-K46-K47,0) -> 0 | ... AH48: =MAX(Supply!AH12-AH46-AH47,0) -> 0
A49: Industrial from groundwater (Conditional) | B49: M m³/yr | C49: Industrial second draw on GW | D49: =MIN(Supply!D13*Inputs!$B$54,MAX(Supply!D8-D46,0)) -> 389.62702 | E49: =MIN(Supply!E13*Inputs!$B$54,MAX(Supply!E8-E46,0)) -> 403.93297 | F49: =MIN(Supply!F13*Inputs!$B$54,MAX(Supply!F8-F46,0)) -> 418.62358 | G49: =MIN(Supply!G13*Inputs!$B$54,MAX(Supply!G8-G46,0)) -> 433.70799 | H49: =MIN(Supply!H13*Inputs!$B$54,MAX(Supply!H8-H46,0)) -> 449.19554 | I49: =MIN(Supply!I13*Inputs!$B$54,MAX(Supply!I8-I46,0)) -> 465.0958 | J49: =MIN(Supply!J13*Inputs!$B$54,MAX(Supply!J8-J46,0)) -> 481.4185 | K49: =MIN(Supply!K13*Inputs!$B$54,MAX(Supply!K8-K46,0)) -> 498.17365 | ... AH49: =MIN(Supply!AH13*Inputs!$B$54,MAX(Supply!AH8-AH46,0)) -> 1029.4841
A50: Industrial from GMMR (Conditional) | B50: M m³/yr | C50: Industrial then GMMR | D50: =MIN(MAX(Supply!D13-D49,0)*Inputs!$B$55,MAX(Supply!D9-D47,0)) -> 0 | E50: =MIN(MAX(Supply!E13-E49,0)*Inputs!$B$55,MAX(Supply!E9-E47,0)) -> 0 | F50: =MIN(MAX(Supply!F13-F49,0)*Inputs!$B$55,MAX(Supply!F9-F47,0)) -> 0 | G50: =MIN(MAX(Supply!G13-G49,0)*Inputs!$B$55,MAX(Supply!G9-G47,0)) -> 0 | H50: =MIN(MAX(Supply!H13-H49,0)*Inputs!$B$55,MAX(Supply!H9-H47,0)) -> 0 | I50: =MIN(MAX(Supply!I13-I49,0)*Inputs!$B$55,MAX(Supply!I9-I47,0)) -> 0 | J50: =MIN(MAX(Supply!J13-J49,0)*Inputs!$B$55,MAX(Supply!J9-J47,0)) -> 0 | K50: =MIN(MAX(Supply!K13-K49,0)*Inputs!$B$55,MAX(Supply!K9-K47,0)) -> 0 | ... AH50: =MIN(MAX(Supply!AH13-AH49,0)*Inputs!$B$55,MAX(Supply!AH9-AH47,0)) -> 0
A51: Industrial from desalination (Conditional) | B51: M m³/yr | C51: Industrial residual desal | D51: =MAX(Supply!D13-D49-D50,0) -> 0 | E51: =MAX(Supply!E13-E49-E50,0) -> 0 | F51: =MAX(Supply!F13-F49-F50,0) -> 0 | G51: =MAX(Supply!G13-G49-G50,0) -> 0 | H51: =MAX(Supply!H13-H49-H50,0) -> 0 | I51: =MAX(Supply!I13-I49-I50,0) -> 0 | J51: =MAX(Supply!J13-J49-J50,0) -> 0 | K51: =MAX(Supply!K13-K49-K50,0) -> 0 | ... AH51: =MAX(Supply!AH13-AH49-AH50,0) -> 0
A52: Agriculture from groundwater (Conditional) | B52: M m³/yr | C52: Agriculture draw on GW after recycled | D52: =MIN(MAX(D14-D45-D58,0)*Inputs!$B$56,MAX(D8-D46-D49,0)) -> 4826.151 | E52: =MIN(MAX(E14-E45-E58,0)*Inputs!$B$56,MAX(E8-E46-E49,0)) -> 4711.2009 | F52: =MIN(MAX(F14-F45-F58,0)*Inputs!$B$56,MAX(F8-F46-F49,0)) -> 4597.3421 | G52: =MIN(MAX(G14-G45-G58,0)*Inputs!$B$56,MAX(G8-G46-G49,0)) -> 4484.5443 | H52: =MIN(MAX(H14-H45-H58,0)*Inputs!$B$56,MAX(H8-H46-H49,0)) -> 4372.7773 | I52: =MIN(MAX(I14-I45-I58,0)*Inputs!$B$56,MAX(I8-I46-I49,0)) -> 4262.0108 | J52: =MIN(MAX(J14-J45-J58,0)*Inputs!$B$56,MAX(J8-J46-J49,0)) -> 4152.2148 | K52: =MIN(MAX(K14-K45-K58,0)*Inputs!$B$56,MAX(K8-K46-K49,0)) -> 4043.3592 | ... AH52: =MIN(MAX(AH14-AH45-AH58,0)*Inputs!$B$56,MAX(AH8-AH46-AH49,0)) -> 1730.6903
A53: Agriculture from GMMR (Conditional) | B53: M m³/yr | C53: Agriculture then GMMR | D53: =MIN(MAX(MAX(D14-D45-D58,0)-D52,0)*Inputs!$B$57,MAX(D9-D47-D50,0)) -> 912 | E53: =MIN(MAX(MAX(E14-E45-E58,0)-E52,0)*Inputs!$B$57,MAX(E9-E47-E50,0)) -> 893.76 | F53: =MIN(MAX(MAX(F14-F45-F58,0)-F52,0)*Inputs!$B$57,MAX(F9-F47-F50,0)) -> 875.8848 | G53: =MIN(MAX(MAX(G14-G45-G58,0)-G52,0)*Inputs!$B$57,MAX(G9-G47-G50,0)) -> 858.3671 | H53: =MIN(MAX(MAX(H14-H45-H58,0)-H52,0)*Inputs!$B$57,MAX(H9-H47-H50,0)) -> 841.19976 | I53: =MIN(MAX(MAX(I14-I45-I58,0)-I52,0)*Inputs!$B$57,MAX(I9-I47-I50,0)) -> 824.37577 | J53: =MIN(MAX(MAX(J14-J45-J58,0)-J52,0)*Inputs!$B$57,MAX(J9-J47-J50,0)) -> 807.88825 | K53: =MIN(MAX(MAX(K14-K45-K58,0)-K52,0)*Inputs!$B$57,MAX(K9-K47-K50,0)) -> 791.73049 | ... AH53: =MIN(MAX(MAX(AH14-AH45-AH58,0)-AH52,0)*Inputs!$B$57,MAX(AH9-AH47-AH50,0)) -> 497.4817
A54: Agriculture from desalination (Conditional) | B54: M m³/yr | C54: Agriculture residual desal | D54: 0 | E54: 0 | F54: 0 | G54: 0 | H54: 0 | I54: 0 | J54: 0 | K54: 0 | L54: 0 | M54: 0 | N54: 0 | O54: 0 | P54: 0 | Q54: 0 | R54: 0 | S54: 0 | T54: 0 | U54: 0 | V54: 0 | W54: 0 | X54: 0 | Y54: 0 | Z54: 0 | AA54: 0 | AB54: 0 | AC54: 0 | AD54: 0 | AE54: 0 | AF54: 0 | AG54: 0 | AH54: 0
A55: Trees from desalination (Conditional) | B55: M m³/yr | C55: Tree residual after recycled | D55: =MAX(Supply!D6-Supply!D44,0) -> 0 | E55: =MAX(Supply!E6-Supply!E44,0) -> 0 | F55: =MAX(Supply!F6-Supply!F44,0) -> 0 | G55: =MAX(Supply!G6-Supply!G44,0) -> 0 | H55: =MAX(Supply!H6-Supply!H44,0) -> 0 | I55: =MAX(Supply!I6-Supply!I44,0) -> 0 | J55: =MAX(Supply!J6-Supply!J44,0) -> 0 | K55: =MAX(Supply!K6-Supply!K44,0) -> 14.725489 | ... AH55: =MAX(Supply!AH6-Supply!AH44,0) -> 326.45942
A56: CHECK: allocated demand incl recycled (Conditional) | B56: M m³/yr | C56: Should equal total demand | D56: =D46+D47+D48+D49+D50+D51+D52+D53+D54+D55+D44+D45+D58+D65 -> 7039.5344 | E56: =E46+E47+E48+E49+E50+E51+E52+E53+E54+E55+E44+E45+E58+E65 -> 7126.1736 | F56: =F46+F47+F48+F49+F50+F51+F52+F53+F54+F55+F44+F45+F58+F65 -> 7211.709 | G56: =G46+G47+G48+G49+G50+G51+G52+G53+G54+G55+G44+G45+G58+G65 -> 7296.1685 | H56: =H46+H47+H48+H49+H50+H51+H52+H53+H54+H55+H44+H45+H58+H65 -> 7379.5803 | I56: =I46+I47+I48+I49+I50+I51+I52+I53+I54+I55+I44+I45+I58+I65 -> 7461.9721 | J56: =J46+J47+J48+J49+J50+J51+J52+J53+J54+J55+J44+J45+J58+J65 -> 7543.3721 | K56: =K46+K47+K48+K49+K50+K51+K52+K53+K54+K55+K44+K45+K58+K65 -> 7678.5583 | ... AH56: =AH46+AH47+AH48+AH49+AH50+AH51+AH52+AH53+AH54+AH55+AH44+AH45+AH58+AH65 -> 9820.5736
A57: Desalination required total (Conditional) | B57: M m³/yr | C57: Sum of desal allocations under Conditional | D57: =D48+D51+D55 -> 0 | E57: =E48+E51+E55 -> 0 | F57: =F48+F51+F55 -> 0 | G57: =G48+G51+G55 -> 0 | H57: =H48+H51+H55 -> 0 | I57: =I48+I51+I55 -> 0 | J57: =J48+J51+J55 -> 0 | K57: =K48+K51+K55 -> 14.725489 | ... AH57: =AH48+AH51+AH55 -> 326.45942
A58: Surface water to agriculture (Conditional) | B58: M m³/yr | C58: min(SW available, ag residual after recycled) | D58: =MIN(D11,MAX(D14-D45,0)) -> 60 | E58: =MIN(E11,MAX(E14-E45,0)) -> 59.4 | F58: =MIN(F11,MAX(F14-F45,0)) -> 58.806 | G58: =MIN(G11,MAX(G14-G45,0)) -> 58.21794 | H58: =MIN(H11,MAX(H14-H45,0)) -> 57.635761 | I58: =MIN(I11,MAX(I14-I45,0)) -> 57.059403 | J58: =MIN(J11,MAX(J14-J45,0)) -> 56.488809 | K58: =MIN(K11,MAX(K14-K45,0)) -> 55.923921 | ... AH58: =MIN(AH11,MAX(AH14-AH45,0)) -> 44.382022
A59: Recycled water used total (Conditional) | B59: M m³/yr | C59: Trees + Agriculture from recycled water | D59: =D44+D45 -> 7.8422198 | E59: =E44+E45 -> 16.957145 | F59: =F44+F45 -> 26.309221 | G59: =G44+G45 -> 35.894206 | H59: =H44+H45 -> 45.707904 | I59: =I44+I45 -> 55.74616 | J59: =J44+J45 -> 66.004866 | K59: =K44+K45 -> 76.479957 | ... AH59: =AH44+AH45 -> 368.40097
A60: Total water supply (Conditional) | B60: M m³/yr | C60: GW + GMMR + desal + recycled | D60: =D46+D49+D52+D65+D47+D50+D53+D58+D57+D59 -> 7039.5344 | E60: =E46+E49+E52+E65+E47+E50+E53+E58+E57+E59 -> 7126.1736 | F60: =F46+F49+F52+F65+F47+F50+F53+F58+F57+F59 -> 7211.709 | G60: =G46+G49+G52+G65+G47+G50+G53+G58+G57+G59 -> 7296.1685 | H60: =H46+H49+H52+H65+H47+H50+H53+H58+H57+H59 -> 7379.5803 | I60: =I46+I49+I52+I65+I47+I50+I53+I58+I57+I59 -> 7461.9721 | J60: =J46+J49+J52+J65+J47+J50+J53+J58+J57+J59 -> 7543.3721 | K60: =K46+K49+K52+K65+K47+K50+K53+K58+K57+K59 -> 7678.5583 | ... AH60: =AH46+AH49+AH52+AH65+AH47+AH50+AH53+AH58+AH57+AH59 -> 9820.5736
A61: Share: Local groundwater (Conditional) | B61: % | D61: =(D46+D49+D52+D65)/D5 -> 0.86080866 | E61: =(E46+E49+E52+E65)/E5 -> 0.86386563 | F61: =(F46+F49+F52+F65)/F5 -> 0.86674448 | G61: =(G46+G49+G52+G65)/G5 -> 0.86945487 | H61: =(H46+H49+H52+H65)/H5 -> 0.87200581 | I61: =(I46+I49+I52+I65)/I5 -> 0.87440568 | J61: =(J46+J49+J52+J65)/J5 -> 0.87666233 | K61: =(K46+K49+K52+K65)/K5 -> 0.87772967 | ... AH61: =(AH46+AH49+AH52+AH65)/AH5 -> 0.87406804
A62: Share: GMMR pipeline (Conditional) | B62: % | D62: =(D47+D50+D53)/D5 -> 0.12955402 | E62: =(E47+E50+E53)/E5 -> 0.12541934 | F62: =(F47+F50+F53)/F5 -> 0.12145315 | G62: =(G47+G50+G53)/G5 -> 0.11764628 | H62: =(H47+H50+H53)/H5 -> 0.11399019 | I62: =(I47+I50+I53)/I5 -> 0.11047693 | J62: =(J47+J50+J53)/J5 -> 0.10709909 | K62: =(K47+K50+K53)/K5 -> 0.10310926 | ... AH62: =(AH47+AH50+AH53)/AH5 -> 0.050657092
A63: Share: Desalination (Conditional) | B63: % | D63: =D57/Supply!D5 -> 0 | E63: =E57/Supply!E5 -> 0 | F63: =F57/Supply!F5 -> 0 | G63: =G57/Supply!G5 -> 0 | H63: =H57/Supply!H5 -> 0 | I63: =I57/Supply!I5 -> 0 | J63: =J57/Supply!J5 -> 0 | K63: =K57/Supply!K5 -> 0.0019177414 | ... AH63: =AH57/Supply!AH5 -> 0.033242398
A64: Share: Treated wastewater (Conditional) | B64: % | D64: =D59/Supply!D5 -> 0.0011140254 | E64: =E59/Supply!E5 -> 0.0023795582 | F64: =F59/Supply!F5 -> 0.0036481258 | G64: =G59/Supply!G5 -> 0.0049195967 | H64: =H59/Supply!H5 -> 0.0061938352 | I64: =I59/Supply!I5 -> 0.0074707006 | J64: =J59/Supply!J5 -> 0.0087500477 | K64: =K59/Supply!K5 -> 0.0099601976 | ... AH64: =AH59/Supply!AH5 -> 0.037513182
A65: Ag from groundwater (overdraft, Conditional) | B65: M m³/yr | C65: Residual ag demand absorbed by private wells when desal hits cap | D65: =MAX(MAX(D14-D45-D58,0)-D52-D53,0) -> 59.692163 | E65: =MAX(MAX(E14-E45-E58,0)-E52-E53,0) -> 246.05645 | F65: =MAX(MAX(F14-F45-F58,0)-F52-F53,0) -> 429.35896 | G65: =MAX(MAX(G14-G45-G58,0)-G52-G53,0) -> 609.65954 | H65: =MAX(MAX(H14-H45-H58,0)-H52-H53,0) -> 787.01753 | I65: =MAX(MAX(I14-I45-I58,0)-I52-I53,0) -> 961.49177 | J65: =MAX(MAX(J14-J45-J58,0)-J52-J53,0) -> 1133.1407 | K65: =MAX(MAX(K14-K45-K58,0)-K52-K53,0) -> 1342.0466 | ... AH65: =MAX(MAX(AH14-AH45-AH58,0)-AH52-AH53,0) -> 4771.101
A66: CHECK: Supply − Demand | B66: M m³/yr | C66: Should equal zero | D66: =D60-Supply!D5 -> 0 | E66: =E60-Supply!E5 -> 0 | F66: =F60-Supply!F5 -> 0 | G66: =G60-Supply!G5 -> 0 | H66: =H60-Supply!H5 -> 0 | I66: =I60-Supply!I5 -> 0 | J66: =J60-Supply!J5 -> 0 | K66: =K60-Supply!K5 -> 0 | ... AH66: =AH60-Supply!AH5 -> 0

Sheet Energy
A1: Electricity Demand for Water Supply — Libya (2020–2050)
A3: Metric | B3: Units | C3: Notes | D3: 2020 | E3: 2021 | F3: 2022 | G3: 2023 | H3: 2024 | I3: 2025 | J3: 2026 | K3: 2027 | L3: 2028 | M3: 2029 | N3: 2030 | O3: 2031 | P3: 2032 | Q3: 2033 | R3: 2034 | S3: 2035 | T3: 2036 | U3: 2037 | V3: 2038 | W3: 2039 | X3: 2040 | Y3: 2041 | Z3: 2042 | AA3: 2043 | AB3: 2044 | AC3: 2045 | AD3: 2046 | AE3: 2047 | AF3: 2048 | AG3: 2049 | AH3: 2050
A5: EI local groundwater | B5: kWh/m³ | C5: EI_GW_2020 × (1+rise)^(year-2020) | D5: =Inputs!$B$26*(1+Inputs!$B$27)^(D$3-2020) -> 0.35 | E5: =Inputs!$B$26*(1+Inputs!$B$27)^(E$3-2020) -> 0.35525 | F5: =Inputs!$B$26*(1+Inputs!$B$27)^(F$3-2020) -> 0.36057875 | G5: =Inputs!$B$26*(1+Inputs!$B$27)^(G$3-2020) -> 0.36598743 | H5: =Inputs!$B$26*(1+Inputs!$B$27)^(H$3-2020) -> 0.37147724 | I5: =Inputs!$B$26*(1+Inputs!$B$27)^(I$3-2020) -> 0.3770494 | J5: =Inputs!$B$26*(1+Inputs!$B$27)^(J$3-2020) -> 0.38270514 | K5: =Inputs!$B$26*(1+Inputs!$B$27)^(K$3-2020) -> 0.38844572 | ... AH5: =Inputs!$B$26*(1+Inputs!$B$27)^(AH$3-2020) -> 0.54707808
A6: EI pipeline (GMMR) | B6: kWh/m³ | C6: EI_pipe × (1+rise)^(year-2020) | D6: =Inputs!$B$28*(1+Inputs!$B$29)^(D$3-2020) -> 1.8 | E6: =Inputs!$B$28*(1+Inputs!$B$29)^(E$3-2020) -> 1.818 | F6: =Inputs!$B$28*(1+Inputs!$B$29)^(F$3-2020) -> 1.83618 | G6: =Inputs!$B$28*(1+Inputs!$B$29)^(G$3-2020) -> 1.8545418 | H6: =Inputs!$B$28*(1+Inputs!$B$29)^(H$3-2020) -> 1.8730872 | I6: =Inputs!$B$28*(1+Inputs!$B$29)^(I$3-2020) -> 1.8918181 | J6: =Inputs!$B$28*(1+Inputs!$B$29)^(J$3-2020) -> 1.9107363 | K6: =Inputs!$B$28*(1+Inputs!$B$29)^(K$3-2020) -> 1.9298436 | ... AH6: =Inputs!$B$28*(1+Inputs!$B$29)^(AH$3-2020) -> 2.426128
A7: EI desalination (SWRO) | B7: kWh/m³ | C7: Linear from EI_2020 to EI_2050 | D7: =Inputs!$B$30+(Inputs!$B$31-Inputs!$B$30)*(D$3-2020)/30 -> 3.5 | E7: =Inputs!$B$30+(Inputs!$B$31-Inputs!$B$30)*(E$3-2020)/30 -> 3.4833333 | F7: =Inputs!$B$30+(Inputs!$B$31-Inputs!$B$30)*(F$3-2020)/30 -> 3.4666667 | G7: =Inputs!$B$30+(Inputs!$B$31-Inputs!$B$30)*(G$3-2020)/30 -> 3.45 | H7: =Inputs!$B$30+(Inputs!$B$31-Inputs!$B$30)*(H$3-2020)/30 -> 3.4333333 | I7: =Inputs!$B$30+(Inputs!$B$31-Inputs!$B$30)*(I$3-2020)/30 -> 3.4166667 | J7: =Inputs!$B$30+(Inputs!$B$31-Inputs!$B$30)*(J$3-2020)/30 -> 3.4 | K7: =Inputs!$B$30+(Inputs!$B$31-Inputs!$B$30)*(K$3-2020)/30 -> 3.3833333 | ... AH7: =Inputs!$B$30+(Inputs!$B$31-Inputs!$B$30)*(AH$3-2020)/30 -> 3
A8: Energy: Surface water | B8: GWh/yr | C8: EI × volume (low) | D8: =0.2*Supply!D7 -> 12 | E8: =0.2*Supply!E7 -> 11.88 | F8: =0.2*Supply!F7 -> 11.7612 | G8: =0.2*Supply!G7 -> 11.643588 | H8: =0.2*Supply!H7 -> 11.527152 | I8: =0.2*Supply!I7 -> 11.411881 | J8: =0.2*Supply!J7 -> 11.297762 | K8: =0.2*Supply!K7 -> 11.184784 | ... AH8: =0.2*Supply!AH7 -> 8.8764045
A9: Energy: Local groundwater | B9: GWh/yr | C9: EI × volume (M m³) | D9: =D5*(Supply!D18+Supply!D21+Supply!D24+Supply!D39) -> 2120.8923 | E9: =E5*(Supply!E18+Supply!E21+Supply!E24+Supply!E39) -> 2189.904 | F9: =F5*(Supply!F18+Supply!F21+Supply!F24+Supply!F39) -> 2259.9713 | G9: =G5*(Supply!G18+Supply!G21+Supply!G24+Supply!G39) -> 2331.1153 | H9: =H5*(Supply!H18+Supply!H21+Supply!H24+Supply!H39) -> 2403.3578 | I9: =I5*(Supply!I18+Supply!I21+Supply!I24+Supply!I39) -> 2476.721 | J9: =J5*(Supply!J18+Supply!J21+Supply!J24+Supply!J39) -> 2551.228 | K9: =K5*(Supply!K18+Supply!K21+Supply!K24+Supply!K39) -> 2629.2895 | ... AH9: =AH5*(Supply!AH18+Supply!AH21+Supply!AH24+Supply!AH39) -> 4762.5454
A10: Energy: Pipeline (GMMR) | B10: GWh/yr | C10: EI × volume | D10: =D6*(Supply!D19+Supply!D22+Supply!D25) -> 1641.6 | E10: =E6*(Supply!E19+Supply!E22+Supply!E25) -> 1624.8557 | F10: =F6*(Supply!F19+Supply!F22+Supply!F25) -> 1608.2822 | G10: =G6*(Supply!G19+Supply!G22+Supply!G25) -> 1591.8777 | H10: =H6*(Supply!H19+Supply!H22+Supply!H25) -> 1575.6405 | I10: =I6*(Supply!I19+Supply!I22+Supply!I25) -> 1559.569 | J10: =J6*(Supply!J19+Supply!J22+Supply!J25) -> 1543.6614 | K10: =K6*(Supply!K19+Supply!K22+Supply!K25) -> 1527.916 | ... AH10: =AH6*(Supply!AH19+Supply!AH22+Supply!AH25) -> 1206.9543
A11: Energy: Desalination (total) (DESAL) | B11: GWh/yr | C11: EI × volume | D11: =D7*Supply!D29 -> 0 | E11: =E7*Supply!E29 -> 0 | F11: =F7*Supply!F29 -> 0 | G11: =G7*Supply!G29 -> 0 | H11: =H7*Supply!H29 -> 0 | I11: =I7*Supply!I29 -> 0 | J11: =J7*Supply!J29 -> 0 | K11: =K7*Supply!K29 -> 164.44681 | ... AH11: =AH7*Supply!AH29 -> 1609.3439
A12: of which: for tree programme | B12: GWh/yr | C12: EI × incremental desal volume | D12: =D7*Supply!D31 -> 0 | E12: =E7*Supply!E31 -> 0 | F12: =F7*Supply!F31 -> 0 | G12: =G7*Supply!G31 -> 0 | H12: =H7*Supply!H31 -> 0 | I12: =I7*Supply!I31 -> 0 | J12: =J7*Supply!J31 -> 0 | K12: =K7*Supply!K31 -> 164.44681 | ... AH12: =AH7*Supply!AH31 -> 1609.3439
A13: EI recycled water | B13: kWh/m³ | C13: Linear from EI_2020 to EI_2050 | D13: =Inputs!B45+(Inputs!B46-Inputs!B45)*(D3-2020)/30 -> 0.8 | E13: =Inputs!B45+(Inputs!B46-Inputs!B45)*(E3-2020)/30 -> 0.795 | F13: =Inputs!B45+(Inputs!B46-Inputs!B45)*(F3-2020)/30 -> 0.79 | G13: =Inputs!B45+(Inputs!B46-Inputs!B45)*(G3-2020)/30 -> 0.785 | H13: =Inputs!B45+(Inputs!B46-Inputs!B45)*(H3-2020)/30 -> 0.78 | I13: =Inputs!B45+(Inputs!B46-Inputs!B45)*(I3-2020)/30 -> 0.775 | J13: =Inputs!B45+(Inputs!B46-Inputs!B45)*(J3-2020)/30 -> 0.77 | K13: =Inputs!B45+(Inputs!B46-Inputs!B45)*(K3-2020)/30 -> 0.765 | L13: =Inputs!B45+(Inputs!B46-Inputs!B45)*(L3-2020)/30 -> 0.76 | M13: =Inputs!B45+(Inputs!B46-Inputs!B45)*(M3-2020)/30 -> 0.755 | N13: =Inputs!B45+(Inputs!B46-Inputs!B45)*(N3-2020)/30 -> 0.75 | O13: =Inputs!B45+(Inputs!B46-Inputs!B45)*(O3-2020)/30 -> 0.745 | P13: =Inputs!B45+(Inputs!B46-Inputs!B45)*(P3-2020)/30 -> 0.74 | Q13: =Inputs!B45+(Inputs!B46-Inputs!B45)*(Q3-2020)/30 -> 0.735 | R13: =Inputs!B45+(Inputs!B46-Inputs!B45)*(R3-2020)/30 -> 0.73 | S13: =Inputs!B45+(Inputs!B46-Inputs!B45)*(S3-2020)/30 -> 0.725 | T13: =Inputs!B45+(Inputs!B46-Inputs!B45)*(T3-2020)/30 -> 0.72 | U13: =Inputs!B45+(Inputs!B46-Inputs!B45)*(U3-2020)/30 -> 0.715 | V13: =Inputs!B45+(Inputs!B46-Inputs!B45)*(V3-2020)/30 -> 0.71 | W13: =Inputs!B45+(Inputs!B46-Inputs!B45)*(W3-2020)/30 -> 0.705 | X13: =Inputs!B45+(Inputs!B46-Inputs!B45)*(X3-2020)/30 -> 0.7 | Y13: =Inputs!B45+(Inputs!B46-Inputs!B45)*(Y3-2020)/30 -> 0.695 | Z13: =Inputs!B45+(Inputs!B46-Inputs!B45)*(Z3-2020)/30 -> 0.69 | AA13: =Inputs!B45+(Inputs!B46-Inputs!B45)*(AA3-2020)/30 -> 0.685 | AB13: =Inputs!B45+(Inputs!B46-Inputs!B45)*(AB3-2020)/30 -> 0.68 | AC13: =Inputs!B45+(Inputs!B46-Inputs!B45)*(AC3-2020)/30 -> 0.675 | AD13: =Inputs!B45+(Inputs!B46-Inputs!B45)*(AD3-2020)/30 -> 0.67 | AE13: =Inputs!B45+(Inputs!B46-Inputs!B45)*(AE3-2020)/30 -> 0.665 | AF13: =Inputs!B45+(Inputs!B46-Inputs!B45)*(AF3-2020)/30 -> 0.66 | AG13: =Inputs!B45+(Inputs!B46-Inputs!B45)*(AG3-2020)/30 -> 0.655 | AH13: =Inputs!B45+(Inputs!B46-Inputs!B45)*(AH3-2020)/30 -> 0.65
A14: Energy: Recycled water (RW) | B14: GWh/yr | C14: EI × recycled water volume | D14: =D13*(Supply!D16+Supply!D17) -> 6.2737758 | E14: =E13*(Supply!E16+Supply!E17) -> 6.8457849 | F14: =F13*(Supply!F16+Supply!F17) -> 7.4229589 | G14: =G13*(Supply!G16+Supply!G17) -> 8.0048159 | H14: =H13*(Supply!H16+Supply!H17) -> 8.5908831 | I14: =I13*(Supply!I16+Supply!I17) -> 9.1806957 | J14: =J13*(Supply!J16+Supply!J17) -> 9.7737975 | K14: =K13*(Supply!K16+Supply!K17) -> 10.36974 | ... AH14: =AH13*(Supply!AH16+Supply!AH17) -> 23.946063
A15: TOTAL electricity demand | B15: GWh/yr | C15: GW + GMMR + Desal | D15: =D8+D9+D10+D11+D14 -> 3780.766 | E15: =E8+E9+E10+E11+E14 -> 3833.4855 | F15: =F8+F9+F10+F11+F14 -> 3887.4376 | G15: =G8+G9+G10+G11+G14 -> 3942.6414 | H15: =H8+H9+H10+H11+H14 -> 3999.1163 | I15: =I8+I9+I10+I11+I14 -> 4056.8825 | J15: =J8+J9+J10+J11+J14 -> 4115.9609 | K15: =K8+K9+K10+K11+K14 -> 4343.2069 | ... AH15: =AH8+AH9+AH10+AH11+AH14 -> 7611.6661
A16: TOTAL electricity demand | B16: TWh/yr | C16: GWh / 1000 | D16: =D15/1000 -> 3.780766 | E16: =E15/1000 -> 3.8334855 | F16: =F15/1000 -> 3.8874376 | G16: =G15/1000 -> 3.9426414 | H16: =H15/1000 -> 3.9991163 | I16: =I15/1000 -> 4.0568825 | J16: =J15/1000 -> 4.1159609 | K16: =K15/1000 -> 4.3432069 | ... AH16: =AH15/1000 -> 7.6116661
B17: PJ/yr | C17: GW * × 0.0036 PJ/GWh | D17: =+D15*Inputs!$B$64 -> 13.610758 | E17: =+E15*Inputs!$B$64 -> 13.800548 | F17: =+F15*Inputs!$B$64 -> 13.994775 | G17: =+G15*Inputs!$B$64 -> 14.193509 | H17: =+H15*Inputs!$B$64 -> 14.396819 | I17: =+I15*Inputs!$B$64 -> 14.604777 | J17: =+J15*Inputs!$B$64 -> 14.817459 | K17: =+K15*Inputs!$B$64 -> 15.635545 | ... AH17: =+AH15*Inputs!$B$64 -> 27.401998
A19: BAU (no tree programme) | B19: PJ/yr | C19: GW + GMMR + desal (excl. tree programme) + RW | D19: =+(D8+D9+D10+(D11-D12)+D14)*Inputs!$B$64 -> 13.610758 | E19: =+(E8+E9+E10+(E11-E12)+E14)*Inputs!$B$64 -> 13.800548 | F19: =+(F8+F9+F10+(F11-F12)+F14)*Inputs!$B$64 -> 13.994775 | G19: =+(G8+G9+G10+(G11-G12)+G14)*Inputs!$B$64 -> 14.193509 | H19: =+(H8+H9+H10+(H11-H12)+H14)*Inputs!$B$64 -> 14.396819 | I19: =+(I8+I9+I10+(I11-I12)+I14)*Inputs!$B$64 -> 14.604777 | J19: =+(J8+J9+J10+(J11-J12)+J14)*Inputs!$B$64 -> 14.817459 | K19: =+(K8+K9+K10+(K11-K12)+K14)*Inputs!$B$64 -> 15.043536 | ... AH19: =+(AH8+AH9+AH10+(AH11-AH12)+AH14)*Inputs!$B$64 -> 21.60836
A20: Unconditional (incl. tree programme) | B20: PJ/yr | C20: GW + GMMR + desal (incl. tree) + RW | D20: =+(D8+D9+D10+D11+D14)*Inputs!$B$64 -> 13.610758 | E20: =+(E8+E9+E10+E11+E14)*Inputs!$B$64 -> 13.800548 | F20: =+(F8+F9+F10+F11+F14)*Inputs!$B$64 -> 13.994775 | G20: =+(G8+G9+G10+G11+G14)*Inputs!$B$64 -> 14.193509 | H20: =+(H8+H9+H10+H11+H14)*Inputs!$B$64 -> 14.396819 | I20: =+(I8+I9+I10+I11+I14)*Inputs!$B$64 -> 14.604777 | J20: =+(J8+J9+J10+J11+J14)*Inputs!$B$64 -> 14.817459 | K20: =+(K8+K9+K10+K11+K14)*Inputs!$B$64 -> 15.635545 | ... AH20: =+(AH8+AH9+AH10+AH11+AH14)*Inputs!$B$64 -> 27.401998
A21: Conditional (incl. tree programme) | B21: PJ/yr | C21: GW + GMMR + desal (incl. tree) + RW | D21: =+(D8+D9+D10+D11+D14)*Inputs!$B$64 -> 13.610758 | E21: =+(E8+E9+E10+E11+E14)*Inputs!$B$64 -> 13.800548 | F21: =+(F8+F9+F10+F11+F14)*Inputs!$B$64 -> 13.994775 | G21: =+(G8+G9+G10+G11+G14)*Inputs!$B$64 -> 14.193509 | H21: =+(H8+H9+H10+H11+H14)*Inputs!$B$64 -> 14.396819 | I21: =+(I8+I9+I10+I11+I14)*Inputs!$B$64 -> 14.604777 | J21: =+(J8+J9+J10+J11+J14)*Inputs!$B$64 -> 14.817459 | K21: =+(K8+K9+K10+K11+K14)*Inputs!$B$64 -> 15.635545 | ... AH21: =+(AH8+AH9+AH10+AH11+AH14)*Inputs!$B$64 -> 27.401998
A23: System-avg EI (kWh/m³) | B23: kWh/m³ | C23: Total energy (GWh) / Total water (M m³) | D23: =D15/Supply!D5 -> 0.53707615 | E23: =E15/Supply!E5 -> 0.53794444 | F23: =F15/Supply!F5 -> 0.53904527 | G23: =G15/Supply!G5 -> 0.54037148 | H23: =H15/Supply!H5 -> 0.5419165 | I23: =I15/Supply!I5 -> 0.54367431 | J23: =J15/Supply!J5 -> 0.54563939 | K23: =K15/Supply!K5 -> 0.56562791 | ... AH23: =AH15/Supply!AH5 -> 0.77507347
A24: Electricity per capita | B24: kWh/cap/yr | C24: Total energy × 1e6 / Population | D24: =D15*1000000/Demand!D5 -> 561.33787 | E24: =E15*1000000/Demand!E5 -> 558.73572 | F24: =F15*1000000/Demand!F5 -> 556.40365 | G24: =G15*1000000/Demand!G5 -> 554.33001 | H24: =H15*1000000/Demand!H5 -> 552.50401 | I24: =I15*1000000/Demand!I5 -> 550.91573 | J24: =J15*1000000/Demand!J5 -> 549.55596 | K24: =K15*1000000/Demand!K5 -> 570.32385 | ... AH24: =AH15*1000000/Demand!AH5 -> 724.44093
A25: Desalination share of energy | B25: % | D25: =D11/D15 -> 0 | E25: =E11/E15 -> 0 | F25: =F11/F15 -> 0 | G25: =G11/G15 -> 0 | H25: =H11/H15 -> 0 | I25: =I11/I15 -> 0 | J25: =J11/J15 -> 0 | K25: =K11/K15 -> 0.037862993 | ... AH25: =AH11/AH15 -> 0.21143123
D30: =+D19/D31 -> 0.11203598
D31: =33746*Inputs!$B$64 -> 121.4856

Sheet Investment
A1: Libya Water Sector — Investment Requirements Estimate (2025–2050)
A4: KEY MACRO ASSUMPTIONS
A5: Parameter | B5: Value | C5: Units | D5: Source / Note
A6: USD per LYD | B6: 0.207 | C6: USD/LYD | D6: Approx mid-2025 official rate. Report (p. 92 fn): 4.142M LYD ≈ 745 MUSD ⇒ ~5.56 LYD/USD
A7: Cost escalation factor (Libya) | B7: 1.3 | C7: multiplier | D7: Construction premium for fragile/conflict context. Edit to test sensitivity.
A8: Discount rate | B8: 0.06 | C8: per year | D8: Public-infrastructure standard (5-8%). Edit to test NPV sensitivity.
A9: Investment horizon — start year | B9: 2025 | C9: year | D9: First year of investment program.
A10: Investment horizon — end year | B10: 2050 | C10: year | D10: End of model horizon.
F11: All values in USD M unless noted
A12: UNIT COST FACTORS BY SOURCE
A13: Source | B13: CAPEX | C13: OPEX | D13: Useful life | E13: Load factor | F13: Source / Note
B14: USD per m³/day | C14: USD per m³ | D14: years | E14: fraction
A15: Desalination (SWRO) | B15: 2000 | C15: 0.65 | D15: 25 | E15: 0.85 | F15: Intl. benchmark $1,500-2,500/m³/d. Report p. 135: GDC plans 5 new plants 240,000 m³/d for LYD 270M (=$233/m³/d) — likely partial; LYD 1.4B for rehab of 5 existing plants. OPEX: SWRO industry $0.50-0.80/m³.
A16: GMMR (groundwater + transfer) | B16: 3000 | C16: 0.3 | D16: 50 | E16: 0.8 | F16: Long-distance fossil-water transfer. Report p. 92 footnote: original 1980s GMMR phases ~$745M for 4.142M LYD. Mostly built; investment is rehab/Phase V-VI per p. 134.
A17: Local groundwater (wells + dist.) | B17: 500 | C17: 0.15 | D17: 35 | E17: 0.7 | F17: Wellfield + distribution. Report p. 85: 101 of 479 western wells dismantled (rehab need). Mostly private wells already exist — public CAPEX is for regulation, GCWW wellfields, MAR. OPEX: pumping energy + maintenance.
A18: Treated wastewater reuse | B18: 2200 | C18: 0.55 | D18: 28 | E18: 0.85 | F18: Tertiary treatment + filtration + storage for ag reuse. Report p. 95: WWTP designed for ag (need secondary biological + filtration + disinfection). MENA benchmarks: $1,800-2,500/m³/d CAPEX; $0.50-0.80/m³ OPEX. Report p. 96 Table 19: LYD 3.9B planned for 2020-2025 wastewater projects.
A19: Surface water (dams + treatment) | B19: 1000 | C19: 0.2 | D19: 60 | E19: 0.55 | F19: Small dams + intake + treatment. Report p. 24-25: limited potential due to evaporation (1,700-6,000 mm/y). Investment mostly rehab of existing small dams.
A21: REPORT-CITED INVESTMENT FIGURES (cross-check, 2020-2025 horizon, USD millions)
A22: Item | B22: LYD millions | C22: USD millions | D22: Source page | E22: Description
A23: GDC — rehab of 5 existing desal plants | B23: 1400 | C23: =B23*$B$6 -> 289.8 | D23: p. 135 | E23: Derna, Sussa, Abu Traba, Zawya, Zourara
A24: GDC — 5 new desal plants (240,000 m³/d) | B24: 270 | C24: =B24*$B$6 -> 55.89 | D24: p. 135 | E24: Already under construction
A25: GCWW — water plants & networks rehab | B25: 54 | C25: =B25*$B$6 -> 11.178 | D25: p. 135 | E25: Existing infrastructure
A26: GCWW — wastewater plants & networks rehab | B26: 273 | C26: =B26*$B$6 -> 56.511 | D26: p. 135 | E26: Existing WW infrastructure
A27: GCWW — supplies & equipment for O&M | B27: 750 | C27: =B27*$B$6 -> 155.25 | D27: p. 136 | E27: Operations support
A28: MMRA — 9 new projects | B28: 117 | C28: =B28*$B$6 -> 24.219 | D28: p. 136 | E28: Capacity increase wells, tanks, pumps
A29: MMRA — 7 existing projects rehab | B29: 396 | C29: =B29*$B$6 -> 81.972 | D29: p. 136 | E29: Rehabilitation
A30: MMRA — reoperation of 1 project | B30: 72 | C30: =B30*$B$6 -> 14.904 | D30: p. 136 | E30: Re-commissioning
A31: MoH — 37 new projects | B31: 883 | C31: =B31*$B$6 -> 182.781 | D31: p. 136 | E31: Coverage and capacity expansion
A32: MoH — 190 existing projects (completion) | B32: 1700 | C32: =B32*$B$6 -> 351.9 | D32: p. 136 | E32: Completion of started projects
A33: MoH — 285 projects on hold | B33: 2500 | C33: =B33*$B$6 -> 517.5 | D33: p. 136 | E33: Restart of paused projects
A34: Total wastewater 2020-2025 (Table 19) | B34: 3905 | C34: =B34*$B$6 -> 808.335 | D34: p. 96 | E34: GCWW + HIB combined; planned 2020-2025
A35: TOTAL (line items above; some overlap) | B35: =SUM(B23:B34) -> 12320 | C35: =SUM(C23:C34) -> 2550.24
A38: BOTTOM-UP INVESTMENT CALCULATION — BAU SCENARIO
A40: Metric | B40: Units | C40: Source | D40: 2020 | E40: 2021 | F40: 2022 | G40: 2023 | H40: 2024 | I40: 2025 | J40: 2026 | K40: 2027 | L40: 2028 | M40: 2029 | N40: 2030 | O40: 2031 | P40: 2032 | Q40: 2033 | R40: 2034 | S40: 2035 | T40: 2036 | U40: 2037 | V40: 2038 | W40: 2039 | X40: 2040 | Y40: 2041 | Z40: 2042 | AA40: 2043 | AB40: 2044 | AC40: 2045 | AD40: 2046 | AE40: 2047 | AF40: 2048 | AG40: 2049 | AH40: 2050
A42: Desalination
A43: Volume | B43: M m³/yr | C43: ← Supply sheet | D43: =Supply!D30 -> 0 | E43: =Supply!E30 -> 0 | F43: =Supply!F30 -> 0 | G43: =Supply!G30 -> 0 | H43: =Supply!H30 -> 0 | I43: =Supply!I30 -> 0 | J43: =Supply!J30 -> 0 | K43: =Supply!K30 -> 0 | ... AH43: =Supply!AH30 -> 0
A44: Capacity required | B44: k m³/day | C44: volume × 1000 / 365 / load_factor | D44: =D43*1000/365/$E15 -> 0 | E44: =E43*1000/365/$E15 -> 0 | F44: =F43*1000/365/$E15 -> 0 | G44: =G43*1000/365/$E15 -> 0 | H44: =H43*1000/365/$E15 -> 0 | I44: =I43*1000/365/$E15 -> 0 | J44: =J43*1000/365/$E15 -> 0 | K44: =K43*1000/365/$E15 -> 0 | ... AH44: =AH43*1000/365/$E15 -> 0
A45: Annualized CAPEX | B45: USD M | C45: capacity × unit_capex × CRF × escal | D45: =IF(D$40<$B$9,0,D44*1000*$B15*($B$8*(1+$B$8)^$D15/((1+$B$8)^$D15-1))*$B$7/1000000) -> 0 | E45: =IF(E$40<$B$9,0,E44*1000*$B15*($B$8*(1+$B$8)^$D15/((1+$B$8)^$D15-1))*$B$7/1000000) -> 0 | F45: =IF(F$40<$B$9,0,F44*1000*$B15*($B$8*(1+$B$8)^$D15/((1+$B$8)^$D15-1))*$B$7/1000000) -> 0 | G45: =IF(G$40<$B$9,0,G44*1000*$B15*($B$8*(1+$B$8)^$D15/((1+$B$8)^$D15-1))*$B$7/1000000) -> 0 | H45: =IF(H$40<$B$9,0,H44*1000*$B15*($B$8*(1+$B$8)^$D15/((1+$B$8)^$D15-1))*$B$7/1000000) -> 0 | I45: =IF(I$40<$B$9,0,I44*1000*$B15*($B$8*(1+$B$8)^$D15/((1+$B$8)^$D15-1))*$B$7/1000000) -> 0 | J45: =IF(J$40<$B$9,0,J44*1000*$B15*($B$8*(1+$B$8)^$D15/((1+$B$8)^$D15-1))*$B$7/1000000) -> 0 | K45: =IF(K$40<$B$9,0,K44*1000*$B15*($B$8*(1+$B$8)^$D15/((1+$B$8)^$D15-1))*$B$7/1000000) -> 0 | ... AH45: =IF(AH$40<$B$9,0,AH44*1000*$B15*($B$8*(1+$B$8)^$D15/((1+$B$8)^$D15-1))*$B$7/1000000) -> 0
A46: OPEX | B46: USD M | C46: volume × unit_opex × escal | D46: =IF(D$40<$B$9,0,D43*$C15*$B$7) -> 0 | E46: =IF(E$40<$B$9,0,E43*$C15*$B$7) -> 0 | F46: =IF(F$40<$B$9,0,F43*$C15*$B$7) -> 0 | G46: =IF(G$40<$B$9,0,G43*$C15*$B$7) -> 0 | H46: =IF(H$40<$B$9,0,H43*$C15*$B$7) -> 0 | I46: =IF(I$40<$B$9,0,I43*$C15*$B$7) -> 0 | J46: =IF(J$40<$B$9,0,J43*$C15*$B$7) -> 0 | K46: =IF(K$40<$B$9,0,K43*$C15*$B$7) -> 0 | ... AH46: =IF(AH$40<$B$9,0,AH43*$C15*$B$7) -> 0
A47: Total annual cost | B47: USD M | C47: New CAPEX + Repl CAPEX + OPEX | D47: =D45+D46 -> 0 | E47: =E45+E46 -> 0 | F47: =F45+F46 -> 0 | G47: =G45+G46 -> 0 | H47: =H45+H46 -> 0 | I47: =I45+I46 -> 0 | J47: =J45+J46 -> 0 | K47: =K45+K46 -> 0 | ... AH47: =AH45+AH46 -> 0
A49: GMMR
A50: Volume | B50: M m³/yr | C50: ← Supply sheet | D50: =Supply!D19+Supply!D22+Supply!D25 -> 912 | E50: =Supply!E19+Supply!E22+Supply!E25 -> 893.76 | F50: =Supply!F19+Supply!F22+Supply!F25 -> 875.8848 | G50: =Supply!G19+Supply!G22+Supply!G25 -> 858.3671 | H50: =Supply!H19+Supply!H22+Supply!H25 -> 841.19976 | I50: =Supply!I19+Supply!I22+Supply!I25 -> 824.37577 | J50: =Supply!J19+Supply!J22+Supply!J25 -> 807.88825 | K50: =Supply!K19+Supply!K22+Supply!K25 -> 791.73049 | ... AH50: =Supply!AH19+Supply!AH22+Supply!AH25 -> 497.4817
A51: Capacity required | B51: k m³/day | C51: volume × 1000 / 365 / load_factor | D51: =D50*1000/365/$E16 -> 3123.2877 | E51: =E50*1000/365/$E16 -> 3060.8219 | F51: =F50*1000/365/$E16 -> 2999.6055 | G51: =G50*1000/365/$E16 -> 2939.6134 | H51: =H50*1000/365/$E16 -> 2880.8211 | I51: =I50*1000/365/$E16 -> 2823.2047 | J51: =J50*1000/365/$E16 -> 2766.7406 | K51: =K50*1000/365/$E16 -> 2711.4058 | ... AH51: =AH50*1000/365/$E16 -> 1703.7044
A52: Annualized CAPEX | B52: USD M | C52: capacity × unit_capex × CRF × escal | D52: =IF(D$40<$B$9,0,D51*1000*$B16*($B$8*(1+$B$8)^$D16/((1+$B$8)^$D16-1))*$B$7/1000000) -> 0 | E52: =IF(E$40<$B$9,0,E51*1000*$B16*($B$8*(1+$B$8)^$D16/((1+$B$8)^$D16-1))*$B$7/1000000) -> 0 | F52: =IF(F$40<$B$9,0,F51*1000*$B16*($B$8*(1+$B$8)^$D16/((1+$B$8)^$D16-1))*$B$7/1000000) -> 0 | G52: =IF(G$40<$B$9,0,G51*1000*$B16*($B$8*(1+$B$8)^$D16/((1+$B$8)^$D16-1))*$B$7/1000000) -> 0 | H52: =IF(H$40<$B$9,0,H51*1000*$B16*($B$8*(1+$B$8)^$D16/((1+$B$8)^$D16-1))*$B$7/1000000) -> 0 | I52: =IF(I$40<$B$9,0,I51*1000*$B16*($B$8*(1+$B$8)^$D16/((1+$B$8)^$D16-1))*$B$7/1000000) -> 698.5532 | J52: =IF(J$40<$B$9,0,J51*1000*$B16*($B$8*(1+$B$8)^$D16/((1+$B$8)^$D16-1))*$B$7/1000000) -> 684.58214 | K52: =IF(K$40<$B$9,0,K51*1000*$B16*($B$8*(1+$B$8)^$D16/((1+$B$8)^$D16-1))*$B$7/1000000) -> 670.8905 | ... AH52: =IF(AH$40<$B$9,0,AH51*1000*$B16*($B$8*(1+$B$8)^$D16/((1+$B$8)^$D16-1))*$B$7/1000000) -> 421.55222
A53: OPEX | B53: USD M | C53: volume × unit_opex × escal | D53: =IF(D$40<$B$9,0,D50*$C16*$B$7) -> 0 | E53: =IF(E$40<$B$9,0,E50*$C16*$B$7) -> 0 | F53: =IF(F$40<$B$9,0,F50*$C16*$B$7) -> 0 | G53: =IF(G$40<$B$9,0,G50*$C16*$B$7) -> 0 | H53: =IF(H$40<$B$9,0,H50*$C16*$B$7) -> 0 | I53: =IF(I$40<$B$9,0,I50*$C16*$B$7) -> 321.50655 | J53: =IF(J$40<$B$9,0,J50*$C16*$B$7) -> 315.07642 | K53: =IF(K$40<$B$9,0,K50*$C16*$B$7) -> 308.77489 | ... AH53: =IF(AH$40<$B$9,0,AH50*$C16*$B$7) -> 194.01786
A54: Total annual cost | B54: USD M | C54: New CAPEX + Repl CAPEX + OPEX | D54: =D52+D53 -> 0 | E54: =E52+E53 -> 0 | F54: =F52+F53 -> 0 | G54: =G52+G53 -> 0 | H54: =H52+H53 -> 0 | I54: =I52+I53 -> 1020.0598 | J54: =J52+J53 -> 999.65856 | K54: =K52+K53 -> 979.66539 | ... AH54: =AH52+AH53 -> 615.57008
A56: Local groundwater
A57: Volume | B57: M m³/yr | C57: ← Supply sheet | D57: =Supply!D18+Supply!D21+Supply!D24+Supply!D39 -> 6059.6922 | E57: =Supply!E18+Supply!E21+Supply!E24+Supply!E39 -> 6164.4025 | F57: =Supply!F18+Supply!F21+Supply!F24+Supply!F39 -> 6267.622 | G57: =Supply!G18+Supply!G21+Supply!G24+Supply!G39 -> 6369.3863 | H57: =Supply!H18+Supply!H21+Supply!H24+Supply!H39 -> 6469.7308 | I57: =Supply!I18+Supply!I21+Supply!I24+Supply!I39 -> 6568.6909 | J57: =Supply!J18+Supply!J21+Supply!J24+Supply!J39 -> 6666.3018 | K57: =Supply!K18+Supply!K21+Supply!K24+Supply!K39 -> 6768.7437 | ... AH57: =Supply!AH18+Supply!AH21+Supply!AH24+Supply!AH39 -> 8705.4218
A58: Capacity required | B58: k m³/day | C58: volume × 1000 / 365 / load_factor | D58: =D57*1000/365/$E17 -> 23716.995 | E58: =E57*1000/365/$E17 -> 24126.82 | F58: =F57*1000/365/$E17 -> 24530.81 | G58: =G57*1000/365/$E17 -> 24929.105 | H58: =H57*1000/365/$E17 -> 25321.843 | I58: =I57*1000/365/$E17 -> 25709.162 | J58: =J57*1000/365/$E17 -> 26091.201 | K58: =K57*1000/365/$E17 -> 26492.147 | ... AH58: =AH57*1000/365/$E17 -> 34072.101
A59: Annualized CAPEX | B59: USD M | C59: capacity × unit_capex × CRF × escal | D59: =IF(D$40<$B$9,0,D58*1000*$B17*($B$8*(1+$B$8)^$D17/((1+$B$8)^$D17-1))*$B$7/1000000) -> 0 | E59: =IF(E$40<$B$9,0,E58*1000*$B17*($B$8*(1+$B$8)^$D17/((1+$B$8)^$D17-1))*$B$7/1000000) -> 0 | F59: =IF(F$40<$B$9,0,F58*1000*$B17*($B$8*(1+$B$8)^$D17/((1+$B$8)^$D17-1))*$B$7/1000000) -> 0 | G59: =IF(G$40<$B$9,0,G58*1000*$B17*($B$8*(1+$B$8)^$D17/((1+$B$8)^$D17-1))*$B$7/1000000) -> 0 | H59: =IF(H$40<$B$9,0,H58*1000*$B17*($B$8*(1+$B$8)^$D17/((1+$B$8)^$D17-1))*$B$7/1000000) -> 0 | I59: =IF(I$40<$B$9,0,I58*1000*$B17*($B$8*(1+$B$8)^$D17/((1+$B$8)^$D17-1))*$B$7/1000000) -> 1152.6191 | J59: =IF(J$40<$B$9,0,J58*1000*$B17*($B$8*(1+$B$8)^$D17/((1+$B$8)^$D17-1))*$B$7/1000000) -> 1169.747 | K59: =IF(K$40<$B$9,0,K58*1000*$B17*($B$8*(1+$B$8)^$D17/((1+$B$8)^$D17-1))*$B$7/1000000) -> 1187.7227 | ... AH59: =IF(AH$40<$B$9,0,AH58*1000*$B17*($B$8*(1+$B$8)^$D17/((1+$B$8)^$D17-1))*$B$7/1000000) -> 1527.5548
A60: OPEX | B60: USD M | C60: volume × unit_opex × escal | D60: =IF(D$40<$B$9,0,D57*$C17*$B$7) -> 0 | E60: =IF(E$40<$B$9,0,E57*$C17*$B$7) -> 0 | F60: =IF(F$40<$B$9,0,F57*$C17*$B$7) -> 0 | G60: =IF(G$40<$B$9,0,G57*$C17*$B$7) -> 0 | H60: =IF(H$40<$B$9,0,H57*$C17*$B$7) -> 0 | I60: =IF(I$40<$B$9,0,I57*$C17*$B$7) -> 1280.8947 | J60: =IF(J$40<$B$9,0,J57*$C17*$B$7) -> 1299.9289 | K60: =IF(K$40<$B$9,0,K57*$C17*$B$7) -> 1319.905 | ... AH60: =IF(AH$40<$B$9,0,AH57*$C17*$B$7) -> 1697.5573
A61: Total annual cost | B61: USD M | C61: New CAPEX + Repl CAPEX + OPEX | D61: =D59+D60 -> 0 | E61: =E59+E60 -> 0 | F61: =F59+F60 -> 0 | G61: =G59+G60 -> 0 | H61: =H59+H60 -> 0 | I61: =I59+I60 -> 2433.5138 | J61: =J59+J60 -> 2469.6759 | K61: =K59+K60 -> 2507.6277 | ... AH61: =AH59+AH60 -> 3225.1121
A63: Treated wastewater
A64: Volume | B64: M m³/yr | C64: ← Supply sheet | D64: =Supply!D34 -> 7.8422198 | E64: =Supply!E34 -> 8.6110502 | F64: =Supply!F34 -> 9.3961504 | G64: =Supply!G34 -> 10.197218 | H64: =Supply!H34 -> 11.013953 | I64: =Supply!I34 -> 11.846059 | J64: =Supply!J34 -> 12.693243 | K64: =Supply!K34 -> 13.555216 | ... AH64: =Supply!AH34 -> 36.840097
A65: Capacity required | B65: k m³/day | C65: volume × 1000 / 365 / load_factor | D65: =D64*1000/365/$E18 -> 25.277098 | E65: =E64*1000/365/$E18 -> 27.755198 | F65: =F64*1000/365/$E18 -> 30.285739 | G65: =G64*1000/365/$E18 -> 32.867745 | H65: =H64*1000/365/$E18 -> 35.50025 | I65: =I64*1000/365/$E18 -> 38.182301 | J65: =J64*1000/365/$E18 -> 40.912952 | K65: =K64*1000/365/$E18 -> 43.691269 | ... AH65: =AH64*1000/365/$E18 -> 118.74326
A66: Annualized CAPEX | B66: USD M | C66: capacity × unit_capex × CRF × escal | D66: =IF(D$40<$B$9,0,D65*1000*$B18*($B$8*(1+$B$8)^$D18/((1+$B$8)^$D18-1))*$B$7/1000000) -> 0 | E66: =IF(E$40<$B$9,0,E65*1000*$B18*($B$8*(1+$B$8)^$D18/((1+$B$8)^$D18-1))*$B$7/1000000) -> 0 | F66: =IF(F$40<$B$9,0,F65*1000*$B18*($B$8*(1+$B$8)^$D18/((1+$B$8)^$D18-1))*$B$7/1000000) -> 0 | G66: =IF(G$40<$B$9,0,G65*1000*$B18*($B$8*(1+$B$8)^$D18/((1+$B$8)^$D18-1))*$B$7/1000000) -> 0 | H66: =IF(H$40<$B$9,0,H65*1000*$B18*($B$8*(1+$B$8)^$D18/((1+$B$8)^$D18-1))*$B$7/1000000) -> 0 | I66: =IF(I$40<$B$9,0,I65*1000*$B18*($B$8*(1+$B$8)^$D18/((1+$B$8)^$D18-1))*$B$7/1000000) -> 8.1456097 | J66: =IF(J$40<$B$9,0,J65*1000*$B18*($B$8*(1+$B$8)^$D18/((1+$B$8)^$D18-1))*$B$7/1000000) -> 8.7281523 | K66: =IF(K$40<$B$9,0,K65*1000*$B18*($B$8*(1+$B$8)^$D18/((1+$B$8)^$D18-1))*$B$7/1000000) -> 9.3208637 | ... AH66: =IF(AH$40<$B$9,0,AH65*1000*$B18*($B$8*(1+$B$8)^$D18/((1+$B$8)^$D18-1))*$B$7/1000000) -> 25.332058
A67: OPEX | B67: USD M | C67: volume × unit_opex × escal | D67: =IF(D$40<$B$9,0,D64*$C18*$B$7) -> 0 | E67: =IF(E$40<$B$9,0,E64*$C18*$B$7) -> 0 | F67: =IF(F$40<$B$9,0,F64*$C18*$B$7) -> 0 | G67: =IF(G$40<$B$9,0,G64*$C18*$B$7) -> 0 | H67: =IF(H$40<$B$9,0,H64*$C18*$B$7) -> 0 | I67: =IF(I$40<$B$9,0,I64*$C18*$B$7) -> 8.4699322 | J67: =IF(J$40<$B$9,0,J64*$C18*$B$7) -> 9.0756691 | K67: =IF(K$40<$B$9,0,K64*$C18*$B$7) -> 9.6919797 | ... AH67: =IF(AH$40<$B$9,0,AH64*$C18*$B$7) -> 26.340669
A68: Total annual cost | B68: USD M | C68: New CAPEX + Repl CAPEX + OPEX | D68: =D66+D67 -> 0 | E68: =E66+E67 -> 0 | F68: =F66+F67 -> 0 | G68: =G66+G67 -> 0 | H68: =H66+H67 -> 0 | I68: =I66+I67 -> 16.615542 | J68: =J66+J67 -> 17.803821 | K68: =K66+K67 -> 19.012843 | ... AH68: =AH66+AH67 -> 51.672727
A70: Surface water
A71: Volume | B71: M m³/yr | C71: ← Supply sheet | D71: =Supply!D7 -> 60 | E71: =Supply!E7 -> 59.4 | F71: =Supply!F7 -> 58.806 | G71: =Supply!G7 -> 58.21794 | H71: =Supply!H7 -> 57.635761 | I71: =Supply!I7 -> 57.059403 | J71: =Supply!J7 -> 56.488809 | K71: =Supply!K7 -> 55.923921 | ... AH71: =Supply!AH7 -> 44.382022
A72: Capacity required | B72: k m³/day | C72: volume × 1000 / 365 / load_factor | D72: =D71*1000/365/$E19 -> 298.8792 | E72: =E71*1000/365/$E19 -> 295.89041 | F72: =F71*1000/365/$E19 -> 292.93151 | G72: =G71*1000/365/$E19 -> 290.00219 | H72: =H71*1000/365/$E19 -> 287.10217 | I72: =I71*1000/365/$E19 -> 284.23115 | J72: =J71*1000/365/$E19 -> 281.38884 | K72: =K71*1000/365/$E19 -> 278.57495 | ... AH72: =AH71*1000/365/$E19 -> 221.08106
A73: Annualized CAPEX | B73: USD M | C73: capacity × unit_capex × CRF × escal | D73: =IF(D$40<$B$9,0,D72*1000*$B19*($B$8*(1+$B$8)^$D19/((1+$B$8)^$D19-1))*$B$7/1000000) -> 0 | E73: =IF(E$40<$B$9,0,E72*1000*$B19*($B$8*(1+$B$8)^$D19/((1+$B$8)^$D19-1))*$B$7/1000000) -> 0 | F73: =IF(F$40<$B$9,0,F72*1000*$B19*($B$8*(1+$B$8)^$D19/((1+$B$8)^$D19-1))*$B$7/1000000) -> 0 | G73: =IF(G$40<$B$9,0,G72*1000*$B19*($B$8*(1+$B$8)^$D19/((1+$B$8)^$D19-1))*$B$7/1000000) -> 0 | H73: =IF(H$40<$B$9,0,H72*1000*$B19*($B$8*(1+$B$8)^$D19/((1+$B$8)^$D19-1))*$B$7/1000000) -> 0 | I73: =IF(I$40<$B$9,0,I72*1000*$B19*($B$8*(1+$B$8)^$D19/((1+$B$8)^$D19-1))*$B$7/1000000) -> 22.86311 | J73: =IF(J$40<$B$9,0,J72*1000*$B19*($B$8*(1+$B$8)^$D19/((1+$B$8)^$D19-1))*$B$7/1000000) -> 22.634478 | K73: =IF(K$40<$B$9,0,K72*1000*$B19*($B$8*(1+$B$8)^$D19/((1+$B$8)^$D19-1))*$B$7/1000000) -> 22.408134 | ... AH73: =IF(AH$40<$B$9,0,AH72*1000*$B19*($B$8*(1+$B$8)^$D19/((1+$B$8)^$D19-1))*$B$7/1000000) -> 17.783415
A74: (not used — see Annualized) | C74: kept blank for backward compatibility | D74: 0 | E74: 0 | F74: 0 | G74: 0 | H74: 0 | I74: 0 | J74: 0 | K74: 0 | L74: 0 | M74: 0 | N74: 0 | O74: 0 | P74: 0 | Q74: 0 | R74: 0 | S74: 0 | T74: 0 | U74: 0 | V74: 0 | W74: 0 | X74: 0 | Y74: 0 | Z74: 0 | AA74: 0 | AB74: 0 | AC74: 0 | AD74: 0 | AE74: 0 | AF74: 0 | AG74: 0 | AH74: 0
A75: OPEX | B75: USD M | C75: volume × unit_opex × escal | D75: =IF(D$40<$B$9,0,D71*$C19*$B$7) -> 0 | E75: =IF(E$40<$B$9,0,E71*$C19*$B$7) -> 0 | F75: =IF(F$40<$B$9,0,F71*$C19*$B$7) -> 0 | G75: =IF(G$40<$B$9,0,G71*$C19*$B$7) -> 0 | H75: =IF(H$40<$B$9,0,H71*$C19*$B$7) -> 0 | I75: =IF(I$40<$B$9,0,I71*$C19*$B$7) -> 14.835445 | J75: =IF(J$40<$B$9,0,J71*$C19*$B$7) -> 14.68709 | K75: =IF(K$40<$B$9,0,K71*$C19*$B$7) -> 14.540219 | ... AH75: =IF(AH$40<$B$9,0,AH71*$C19*$B$7) -> 11.539326
A76: Total annual cost | B76: USD M | C76: New CAPEX + Repl CAPEX + OPEX | D76: =D73+D75 -> 0 | E76: =E73+E75 -> 0 | F76: =F73+F75 -> 0 | G76: =G73+G75 -> 0 | H76: =H73+H75 -> 0 | I76: =I73+I75 -> 37.698554 | J76: =J73+J75 -> 37.321569 | K76: =K73+K75 -> 36.948353 | ... AH76: =AH73+AH75 -> 29.322741
A78: AGGREGATED INVESTMENT — BAU SCENARIO (USD millions)
A80: Total Annualized CAPEX | B80: USD M | D80: =SUM(D45,D52,D59,D66,D73) -> 0 | E80: =SUM(E45,E52,E59,E66,E73) -> 0 | F80: =SUM(F45,F52,F59,F66,F73) -> 0 | G80: =SUM(G45,G52,G59,G66,G73) -> 0 | H80: =SUM(H45,H52,H59,H66,H73) -> 0 | I80: =SUM(I45,I52,I59,I66,I73) -> 1882.181 | J80: =SUM(J45,J52,J59,J66,J73) -> 1885.6918 | K80: =SUM(K45,K52,K59,K66,K73) -> 1890.3422 | ... AH80: =SUM(AH45,AH52,AH59,AH66,AH73) -> 1992.2225
A81: Total OPEX | B81: USD M | D81: =SUM(D46,D53,D60,D67,D75) -> 0 | E81: =SUM(E46,E53,E60,E67,E75) -> 0 | F81: =SUM(F46,F53,F60,F67,F75) -> 0 | G81: =SUM(G46,G53,G60,G67,G75) -> 0 | H81: =SUM(H46,H53,H60,H67,H75) -> 0 | I81: =SUM(I46,I53,I60,I67,I75) -> 1625.7066 | J81: =SUM(J46,J53,J60,J67,J75) -> 1638.768 | K81: =SUM(K46,K53,K60,K67,K75) -> 1652.9121 | ... AH81: =SUM(AH46,AH53,AH60,AH67,AH75) -> 1929.4551
A82: TOTAL annual cost | B82: USD M | D82: =D80+D81 -> 0 | E82: =E80+E81 -> 0 | F82: =F80+F81 -> 0 | G82: =G80+G81 -> 0 | H82: =H80+H81 -> 0 | I82: =I80+I81 -> 3507.8876 | J82: =J80+J81 -> 3524.4598 | K82: =K80+K81 -> 3543.2543 | ... AH82: =AH80+AH81 -> 3921.6776
A84: Cumulative annualized CAPEX | B84: USD M | D84: =D80 -> 0 | E84: =D84+E80 -> 0 | F84: =E84+F80 -> 0 | G84: =F84+G80 -> 0 | H84: =G84+H80 -> 0 | I84: =H84+I80 -> 1882.181 | J84: =I84+J80 -> 3767.8728 | K84: =J84+K80 -> 5658.215 | L84: =K84+L80 -> 7552.2437 | ... AH84: =AG84+AH80 -> 50286.024
A87: BOTTOM-UP INVESTMENT CALCULATION — CONDITIONAL SCENARIO
A89: Metric | B89: Units | C89: Source | D89: 2020 | E89: 2021 | F89: 2022 | G89: 2023 | H89: 2024 | I89: 2025 | J89: 2026 | K89: 2027 | L89: 2028 | M89: 2029 | N89: 2030 | O89: 2031 | P89: 2032 | Q89: 2033 | R89: 2034 | S89: 2035 | T89: 2036 | U89: 2037 | V89: 2038 | W89: 2039 | X89: 2040 | Y89: 2041 | Z89: 2042 | AA89: 2043 | AB89: 2044 | AC89: 2045 | AD89: 2046 | AE89: 2047 | AF89: 2048 | AG89: 2049 | AH89: 2050
A91: Desalination
A92: Volume | B92: M m³/yr | C92: ← Supply (Conditional rows) | D92: =Supply!D57 -> 0 | E92: =Supply!E57 -> 0 | F92: =Supply!F57 -> 0 | G92: =Supply!G57 -> 0 | H92: =Supply!H57 -> 0 | I92: =Supply!I57 -> 0 | J92: =Supply!J57 -> 0 | K92: =Supply!K57 -> 14.725489 | ... AH92: =Supply!AH57 -> 326.45942
A93: Capacity required | B93: k m³/day | C93: volume × 1000 / 365 / load_factor | D93: =D92*1000/365/$E15 -> 0 | E93: =E92*1000/365/$E15 -> 0 | F93: =F92*1000/365/$E15 -> 0 | G93: =G92*1000/365/$E15 -> 0 | H93: =H92*1000/365/$E15 -> 0 | I93: =I92*1000/365/$E15 -> 0 | J93: =J92*1000/365/$E15 -> 0 | K93: =K92*1000/365/$E15 -> 47.463301 | ... AH93: =AH92*1000/365/$E15 -> 1052.2463
A94: Annualized CAPEX | B94: USD M | C94: capacity × unit_capex × CRF × escal | D94: =IF(D$89<$B$9,0,D93*1000*$B15*($B$8*(1+$B$8)^$D15/((1+$B$8)^$D15-1))*$B$7/1000000) -> 0 | E94: =IF(E$89<$B$9,0,E93*1000*$B15*($B$8*(1+$B$8)^$D15/((1+$B$8)^$D15-1))*$B$7/1000000) -> 0 | F94: =IF(F$89<$B$9,0,F93*1000*$B15*($B$8*(1+$B$8)^$D15/((1+$B$8)^$D15-1))*$B$7/1000000) -> 0 | G94: =IF(G$89<$B$9,0,G93*1000*$B15*($B$8*(1+$B$8)^$D15/((1+$B$8)^$D15-1))*$B$7/1000000) -> 0 | H94: =IF(H$89<$B$9,0,H93*1000*$B15*($B$8*(1+$B$8)^$D15/((1+$B$8)^$D15-1))*$B$7/1000000) -> 0 | I94: =IF(I$89<$B$9,0,I93*1000*$B15*($B$8*(1+$B$8)^$D15/((1+$B$8)^$D15-1))*$B$7/1000000) -> 0 | J94: =IF(J$89<$B$9,0,J93*1000*$B15*($B$8*(1+$B$8)^$D15/((1+$B$8)^$D15-1))*$B$7/1000000) -> 0 | K94: =IF(K$89<$B$9,0,K93*1000*$B15*($B$8*(1+$B$8)^$D15/((1+$B$8)^$D15-1))*$B$7/1000000) -> 9.6535355 | ... AH94: =IF(AH$89<$B$9,0,AH93*1000*$B15*($B$8*(1+$B$8)^$D15/((1+$B$8)^$D15-1))*$B$7/1000000) -> 214.01582
A95: OPEX | B95: USD M | C95: volume × unit_opex × escal | D95: =IF(D$89<$B$9,0,D92*$C15*$B$7) -> 0 | E95: =IF(E$89<$B$9,0,E92*$C15*$B$7) -> 0 | F95: =IF(F$89<$B$9,0,F92*$C15*$B$7) -> 0 | G95: =IF(G$89<$B$9,0,G92*$C15*$B$7) -> 0 | H95: =IF(H$89<$B$9,0,H92*$C15*$B$7) -> 0 | I95: =IF(I$89<$B$9,0,I92*$C15*$B$7) -> 0 | J95: =IF(J$89<$B$9,0,J92*$C15*$B$7) -> 0 | K95: =IF(K$89<$B$9,0,K92*$C15*$B$7) -> 12.443038 | ... AH95: =IF(AH$89<$B$9,0,AH92*$C15*$B$7) -> 275.85821
A96: Total annual cost | B96: USD M | C96: New CAPEX + Repl CAPEX + OPEX | D96: =D94+D95 -> 0 | E96: =E94+E95 -> 0 | F96: =F94+F95 -> 0 | G96: =G94+G95 -> 0 | H96: =H94+H95 -> 0 | I96: =I94+I95 -> 0 | J96: =J94+J95 -> 0 | K96: =K94+K95 -> 22.096574 | ... AH96: =AH94+AH95 -> 489.87403
A98: GMMR
A99: Volume | B99: M m³/yr | C99: ← Supply (Conditional rows) | D99: =Supply!D47+Supply!D50+Supply!D53 -> 912 | E99: =Supply!E47+Supply!E50+Supply!E53 -> 893.76 | F99: =Supply!F47+Supply!F50+Supply!F53 -> 875.8848 | G99: =Supply!G47+Supply!G50+Supply!G53 -> 858.3671 | H99: =Supply!H47+Supply!H50+Supply!H53 -> 841.19976 | I99: =Supply!I47+Supply!I50+Supply!I53 -> 824.37577 | J99: =Supply!J47+Supply!J50+Supply!J53 -> 807.88825 | K99: =Supply!K47+Supply!K50+Supply!K53 -> 791.73049 | ... AH99: =Supply!AH47+Supply!AH50+Supply!AH53 -> 497.4817
A100: Capacity required | B100: k m³/day | C100: volume × 1000 / 365 / load_factor | D100: =D99*1000/365/$E16 -> 3123.2877 | E100: =E99*1000/365/$E16 -> 3060.8219 | F100: =F99*1000/365/$E16 -> 2999.6055 | G100: =G99*1000/365/$E16 -> 2939.6134 | H100: =H99*1000/365/$E16 -> 2880.8211 | I100: =I99*1000/365/$E16 -> 2823.2047 | J100: =J99*1000/365/$E16 -> 2766.7406 | K100: =K99*1000/365/$E16 -> 2711.4058 | ... AH100: =AH99*1000/365/$E16 -> 1703.7044
A101: Annualized CAPEX | B101: USD M | C101: capacity × unit_capex × CRF × escal | D101: =IF(D$89<$B$9,0,D100*1000*$B16*($B$8*(1+$B$8)^$D16/((1+$B$8)^$D16-1))*$B$7/1000000) -> 0 | E101: =IF(E$89<$B$9,0,E100*1000*$B16*($B$8*(1+$B$8)^$D16/((1+$B$8)^$D16-1))*$B$7/1000000) -> 0 | F101: =IF(F$89<$B$9,0,F100*1000*$B16*($B$8*(1+$B$8)^$D16/((1+$B$8)^$D16-1))*$B$7/1000000) -> 0 | G101: =IF(G$89<$B$9,0,G100*1000*$B16*($B$8*(1+$B$8)^$D16/((1+$B$8)^$D16-1))*$B$7/1000000) -> 0 | H101: =IF(H$89<$B$9,0,H100*1000*$B16*($B$8*(1+$B$8)^$D16/((1+$B$8)^$D16-1))*$B$7/1000000) -> 0 | I101: =IF(I$89<$B$9,0,I100*1000*$B16*($B$8*(1+$B$8)^$D16/((1+$B$8)^$D16-1))*$B$7/1000000) -> 698.5532 | J101: =IF(J$89<$B$9,0,J100*1000*$B16*($B$8*(1+$B$8)^$D16/((1+$B$8)^$D16-1))*$B$7/1000000) -> 684.58214 | K101: =IF(K$89<$B$9,0,K100*1000*$B16*($B$8*(1+$B$8)^$D16/((1+$B$8)^$D16-1))*$B$7/1000000) -> 670.8905 | ... AH101: =IF(AH$89<$B$9,0,AH100*1000*$B16*($B$8*(1+$B$8)^$D16/((1+$B$8)^$D16-1))*$B$7/1000000) -> 421.55222
A102: OPEX | B102: USD M | C102: volume × unit_opex × escal | D102: =IF(D$89<$B$9,0,D99*$C16*$B$7) -> 0 | E102: =IF(E$89<$B$9,0,E99*$C16*$B$7) -> 0 | F102: =IF(F$89<$B$9,0,F99*$C16*$B$7) -> 0 | G102: =IF(G$89<$B$9,0,G99*$C16*$B$7) -> 0 | H102: =IF(H$89<$B$9,0,H99*$C16*$B$7) -> 0 | I102: =IF(I$89<$B$9,0,I99*$C16*$B$7) -> 321.50655 | J102: =IF(J$89<$B$9,0,J99*$C16*$B$7) -> 315.07642 | K102: =IF(K$89<$B$9,0,K99*$C16*$B$7) -> 308.77489 | ... AH102: =IF(AH$89<$B$9,0,AH99*$C16*$B$7) -> 194.01786
A103: Total annual cost | B103: USD M | C103: New CAPEX + Repl CAPEX + OPEX | D103: =D101+D102 -> 0 | E103: =E101+E102 -> 0 | F103: =F101+F102 -> 0 | G103: =G101+G102 -> 0 | H103: =H101+H102 -> 0 | I103: =I101+I102 -> 1020.0598 | J103: =J101+J102 -> 999.65856 | K103: =K101+K102 -> 979.66539 | ... AH103: =AH101+AH102 -> 615.57008
A105: Local groundwater
A106: Volume | B106: M m³/yr | C106: ← Supply (Conditional rows) | D106: =Supply!D46+Supply!D49+Supply!D52+Supply!D65 -> 6059.6922 | E106: =Supply!E46+Supply!E49+Supply!E52+Supply!E65 -> 6156.0564 | F106: =Supply!F46+Supply!F49+Supply!F52+Supply!F65 -> 6250.709 | G106: =Supply!G46+Supply!G49+Supply!G52+Supply!G65 -> 6343.6893 | H106: =Supply!H46+Supply!H49+Supply!H52+Supply!H65 -> 6435.0368 | I106: =Supply!I46+Supply!I49+Supply!I52+Supply!I65 -> 6524.7908 | J106: =Supply!J46+Supply!J49+Supply!J52+Supply!J65 -> 6612.9902 | K106: =Supply!K46+Supply!K49+Supply!K52+Supply!K65 -> 6739.6984 | ... AH106: =Supply!AH46+Supply!AH49+Supply!AH52+Supply!AH65 -> 8583.8495
A107: Capacity required | B107: k m³/day | C107: volume × 1000 / 365 / load_factor | D107: =D106*1000/365/$E17 -> 23716.995 | E107: =E106*1000/365/$E17 -> 24094.154 | F107: =F106*1000/365/$E17 -> 24464.614 | G107: =G106*1000/365/$E17 -> 24828.53 | H107: =H106*1000/365/$E17 -> 25186.054 | I107: =I106*1000/365/$E17 -> 25537.342 | J107: =J106*1000/365/$E17 -> 25882.545 | K107: =K106*1000/365/$E17 -> 26378.467 | ... AH107: =AH106*1000/365/$E17 -> 33596.28
A108: Annualized CAPEX | B108: USD M | C108: capacity × unit_capex × CRF × escal | D108: =IF(D$89<$B$9,0,D107*1000*$B17*($B$8*(1+$B$8)^$D17/((1+$B$8)^$D17-1))*$B$7/1000000) -> 0 | E108: =IF(E$89<$B$9,0,E107*1000*$B17*($B$8*(1+$B$8)^$D17/((1+$B$8)^$D17-1))*$B$7/1000000) -> 0 | F108: =IF(F$89<$B$9,0,F107*1000*$B17*($B$8*(1+$B$8)^$D17/((1+$B$8)^$D17-1))*$B$7/1000000) -> 0 | G108: =IF(G$89<$B$9,0,G107*1000*$B17*($B$8*(1+$B$8)^$D17/((1+$B$8)^$D17-1))*$B$7/1000000) -> 0 | H108: =IF(H$89<$B$9,0,H107*1000*$B17*($B$8*(1+$B$8)^$D17/((1+$B$8)^$D17-1))*$B$7/1000000) -> 0 | I108: =IF(I$89<$B$9,0,I107*1000*$B17*($B$8*(1+$B$8)^$D17/((1+$B$8)^$D17-1))*$B$7/1000000) -> 1144.9158 | J108: =IF(J$89<$B$9,0,J107*1000*$B17*($B$8*(1+$B$8)^$D17/((1+$B$8)^$D17-1))*$B$7/1000000) -> 1160.3923 | K108: =IF(K$89<$B$9,0,K107*1000*$B17*($B$8*(1+$B$8)^$D17/((1+$B$8)^$D17-1))*$B$7/1000000) -> 1182.626 | ... AH108: =IF(AH$89<$B$9,0,AH107*1000*$B17*($B$8*(1+$B$8)^$D17/((1+$B$8)^$D17-1))*$B$7/1000000) -> 1506.2223
A109: OPEX | B109: USD M | C109: volume × unit_opex × escal | D109: =IF(D$89<$B$9,0,D106*$C17*$B$7) -> 0 | E109: =IF(E$89<$B$9,0,E106*$C17*$B$7) -> 0 | F109: =IF(F$89<$B$9,0,F106*$C17*$B$7) -> 0 | G109: =IF(G$89<$B$9,0,G106*$C17*$B$7) -> 0 | H109: =IF(H$89<$B$9,0,H106*$C17*$B$7) -> 0 | I109: =IF(I$89<$B$9,0,I106*$C17*$B$7) -> 1272.3342 | J109: =IF(J$89<$B$9,0,J106*$C17*$B$7) -> 1289.5331 | K109: =IF(K$89<$B$9,0,K106*$C17*$B$7) -> 1314.2412 | ... AH109: =IF(AH$89<$B$9,0,AH106*$C17*$B$7) -> 1673.8507
A110: Total annual cost | B110: USD M | C110: New CAPEX + Repl CAPEX + OPEX | D110: =D108+D109 -> 0 | E110: =E108+E109 -> 0 | F110: =F108+F109 -> 0 | G110: =G108+G109 -> 0 | H110: =H108+H109 -> 0 | I110: =I108+I109 -> 2417.2501 | J110: =J108+J109 -> 2449.9254 | K110: =K108+K109 -> 2496.8672 | ... AH110: =AH108+AH109 -> 3180.073
A112: Treated wastewater
A113: Volume | B113: M m³/yr | C113: ← Supply (Conditional rows) | D113: =Supply!D59 -> 7.8422198 | E113: =Supply!E59 -> 16.957145 | F113: =Supply!F59 -> 26.309221 | G113: =Supply!G59 -> 35.894206 | H113: =Supply!H59 -> 45.707904 | I113: =Supply!I59 -> 55.74616 | J113: =Supply!J59 -> 66.004866 | K113: =Supply!K59 -> 76.479957 | ... AH113: =Supply!AH59 -> 368.40097
A114: Capacity required | B114: k m³/day | C114: volume × 1000 / 365 / load_factor | D114: =D113*1000/365/$E18 -> 25.277098 | E114: =E113*1000/365/$E18 -> 54.65639 | F114: =F113*1000/365/$E18 -> 84.800068 | G114: =G113*1000/365/$E18 -> 115.69446 | H114: =H113*1000/365/$E18 -> 147.32604 | I114: =I113*1000/365/$E18 -> 179.68142 | J114: =J113*1000/365/$E18 -> 212.74735 | K114: =K113*1000/365/$E18 -> 246.51074 | ... AH114: =AH113*1000/365/$E18 -> 1187.4326
A115: Annualized CAPEX | B115: USD M | C115: capacity × unit_capex × CRF × escal | D115: =IF(D$89<$B$9,0,D114*1000*$B18*($B$8*(1+$B$8)^$D18/((1+$B$8)^$D18-1))*$B$7/1000000) -> 0 | E115: =IF(E$89<$B$9,0,E114*1000*$B18*($B$8*(1+$B$8)^$D18/((1+$B$8)^$D18-1))*$B$7/1000000) -> 0 | F115: =IF(F$89<$B$9,0,F114*1000*$B18*($B$8*(1+$B$8)^$D18/((1+$B$8)^$D18-1))*$B$7/1000000) -> 0 | G115: =IF(G$89<$B$9,0,G114*1000*$B18*($B$8*(1+$B$8)^$D18/((1+$B$8)^$D18-1))*$B$7/1000000) -> 0 | H115: =IF(H$89<$B$9,0,H114*1000*$B18*($B$8*(1+$B$8)^$D18/((1+$B$8)^$D18-1))*$B$7/1000000) -> 0 | I115: =IF(I$89<$B$9,0,I114*1000*$B18*($B$8*(1+$B$8)^$D18/((1+$B$8)^$D18-1))*$B$7/1000000) -> 38.332281 | J115: =IF(J$89<$B$9,0,J114*1000*$B18*($B$8*(1+$B$8)^$D18/((1+$B$8)^$D18-1))*$B$7/1000000) -> 45.386392 | K115: =IF(K$89<$B$9,0,K114*1000*$B18*($B$8*(1+$B$8)^$D18/((1+$B$8)^$D18-1))*$B$7/1000000) -> 52.589294 | ... AH115: =IF(AH$89<$B$9,0,AH114*1000*$B18*($B$8*(1+$B$8)^$D18/((1+$B$8)^$D18-1))*$B$7/1000000) -> 253.32058
A116: (not used — see Annualized) | C116: kept blank for backward compatibility | D116: 0 | E116: 0 | F116: 0 | G116: 0 | H116: 0 | I116: 0 | J116: 0 | K116: 0 | L116: 0 | M116: 0 | N116: 0 | O116: 0 | P116: 0 | Q116: 0 | R116: 0 | S116: 0 | T116: 0 | U116: 0 | V116: 0 | W116: 0 | X116: 0 | Y116: 0 | Z116: 0 | AA116: 0 | AB116: 0 | AC116: 0 | AD116: 0 | AE116: 0 | AF116: 0 | AG116: 0 | AH116: 0
A117: OPEX | B117: USD M | C117: volume × unit_opex × escal | D117: =IF(D$89<$B$9,0,D113*$C18*$B$7) -> 0 | E117: =IF(E$89<$B$9,0,E113*$C18*$B$7) -> 0 | F117: =IF(F$89<$B$9,0,F113*$C18*$B$7) -> 0 | G117: =IF(G$89<$B$9,0,G113*$C18*$B$7) -> 0 | H117: =IF(H$89<$B$9,0,H113*$C18*$B$7) -> 0 | I117: =IF(I$89<$B$9,0,I113*$C18*$B$7) -> 39.858504 | J117: =IF(J$89<$B$9,0,J113*$C18*$B$7) -> 47.193479 | K117: =IF(K$89<$B$9,0,K113*$C18*$B$7) -> 54.683169 | ... AH117: =IF(AH$89<$B$9,0,AH113*$C18*$B$7) -> 263.40669
A118: Total annual cost | B118: USD M | C118: New CAPEX + Repl CAPEX + OPEX | D118: =D115+D117 -> 0 | E118: =E115+E117 -> 0 | F118: =F115+F117 -> 0 | G118: =G115+G117 -> 0 | H118: =H115+H117 -> 0 | I118: =I115+I117 -> 78.190785 | J118: =J115+J117 -> 92.579871 | K118: =K115+K117 -> 107.27246 | ... AH118: =AH115+AH117 -> 516.72727
A120: Surface water
A121: Volume | B121: M m³/yr | C121: ← Supply (Conditional rows) | D121: =Supply!D58 -> 60 | E121: =Supply!E58 -> 59.4 | F121: =Supply!F58 -> 58.806 | G121: =Supply!G58 -> 58.21794 | H121: =Supply!H58 -> 57.635761 | I121: =Supply!I58 -> 57.059403 | J121: =Supply!J58 -> 56.488809 | K121: =Supply!K58 -> 55.923921 | ... AH121: =Supply!AH58 -> 44.382022
A122: Capacity required | B122: k m³/day | C122: volume × 1000 / 365 / load_factor | D122: =D121*1000/365/$E19 -> 298.8792 | E122: =E121*1000/365/$E19 -> 295.89041 | F122: =F121*1000/365/$E19 -> 292.93151 | G122: =G121*1000/365/$E19 -> 290.00219 | H122: =H121*1000/365/$E19 -> 287.10217 | I122: =I121*1000/365/$E19 -> 284.23115 | J122: =J121*1000/365/$E19 -> 281.38884 | K122: =K121*1000/365/$E19 -> 278.57495 | ... AH122: =AH121*1000/365/$E19 -> 221.08106
...

Sheet Summary
A1: Libya Water-Energy Model — Summary (2020 vs 2050)
A3: Metric | B3: 2020 | C3: 2050 | D3: CAGR | E3: Notes
A4: Population | B4: =Demand!D5 -> 6735277 | C4: =Demand!AH5 -> 10506952 | D4: =IFERROR((C4/B4)^(1/30)-1,"") -> 0.014933006
A5: GDP per capita (USD) | B5: =Demand!D6 -> 6357 | C5: =Demand!AH6 -> 14556.121 | D5: =IFERROR((C5/B5)^(1/30)-1,"") -> 0.028
A6: Total GDP (M USD) | B6: =Demand!D7 -> 42816.156 | C6: =Demand!AH7 -> 152940.46 | D6: =IFERROR((C6/B6)^(1/30)-1,"") -> 0.04335113
A7: Total water demand (M m³/yr) | B7: =Demand!D19 -> 7039.5344 | C7: =Demand!AH19 -> 9820.5736 | D7: =IFERROR((C7/B7)^(1/30)-1,"") -> 0.011159727
A8: Domestic demand | B8: =Demand!D13 -> 784.22198 | C8: =Demand!AH13 -> 1052.5742 | D8: =IFERROR((C8/B8)^(1/30)-1,"") -> 0.0098583411
A9: Industrial demand | B9: =Demand!D14 -> 389.62702 | C9: =Demand!AH14 -> 1029.4841 | D9: =IFERROR((C9/B9)^(1/30)-1,"") -> 0.032917619
A10: Agricultural demand | B10: =Demand!D15 -> 5865.6854 | C10: =Demand!AH15 -> 7191.0154 | D10: =IFERROR((C10/B10)^(1/30)-1,"") -> 0.0068135421
A11: Tree programme demand | B11: =Demand!D17 -> 0 | C11: =Demand!AH17 -> 547.5 | D11: =IFERROR((C11/B11)^(1/30)-1,"") | E11: ~9% of national water use once fully established (2036+)
A12: Local groundwater (M m³/yr) | B12: =Supply!D8 -> 6000 | C12: =Supply!AH8 -> 3812.7486 | D12: =IFERROR((C12/B12)^(1/30)-1,"") -> -0.015
A13: GMMR pipeline (M m³/yr) | B13: =Supply!D9 -> 912 | C13: =Supply!AH9 -> 497.4817 | D13: =IFERROR((C13/B13)^(1/30)-1,"") -> -0.02 | E13: Now declining at −2%/yr (was +recovery)
A14: Desalination required (M m³/yr) | B14: =Supply!D29 -> 0 | C14: =Supply!AH29 -> 536.44797 | D14: =IFERROR((C14/B14)^(1/30)-1,"") | E14: Makes up deficit
A15: Incremental desal for trees | B15: =Supply!D31 -> 0 | C15: =Supply!AH31 -> 536.44797 | D15: =IFERROR((C15/B15)^(1/30)-1,"")
A16: SWRO capacity for trees (m³/day) | B16: =Supply!D32 -> 0 | C16: =Supply!AH32 -> 1469720.5 | D16: =IFERROR((C16/B16)^(1/30)-1,"") | E16: ≈3× Libya's current operational desal fleet (~526 k m³/d, Brika 2018)
A17: Electricity: groundwater (GWh) | B17: =Energy!D9 -> 2120.8923 | C17: =Energy!AH9 -> 4762.5454 | D17: =IFERROR((C17/B17)^(1/30)-1,"") -> 0.027331688
A18: Electricity: GMMR (GWh) | B18: =Energy!D10 -> 1641.6 | C18: =Energy!AH10 -> 1206.9543 | D18: =IFERROR((C18/B18)^(1/30)-1,"") -> -0.0102
A19: Electricity: desalination (GWh) | B19: =Energy!D11 -> 0 | C19: =Energy!AH11 -> 1609.3439 | D19: =IFERROR((C19/B19)^(1/30)-1,"")
A20: of which: for tree programme (GWh) | B20: =Energy!D12 -> 0 | C20: =Energy!AH12 -> 1609.3439 | D20: =IFERROR((C20/B20)^(1/30)-1,"")
A21: TOTAL electricity (GWh/yr) | B21: =Energy!D15 -> 3780.766 | C21: =Energy!AH15 -> 7611.6661 | D21: =IFERROR((C21/B21)^(1/30)-1,"") -> 0.023599341
A22: TOTAL electricity (TWh/yr) | B22: =Energy!D16 -> 3.780766 | C22: =Energy!AH16 -> 7.6116661 | D22: =IFERROR((C22/B22)^(1/30)-1,"") -> 0.023599341
A23: System-avg EI (kWh/m³) | B23: =Energy!D23 -> 0.53707615 | C23: =Energy!AH23 -> 0.77507347 | D23: =IFERROR((C23/B23)^(1/30)-1,"") -> 0.012302323
A24: Electricity per capita (kWh/cap/yr) | B24: =Energy!D24 -> 561.33787 | C24: =Energy!AH24 -> 724.44093 | D24: =IFERROR((C24/B24)^(1/30)-1,"") -> 0.0085388245
A25: Desal share of energy (%) | B25: =Energy!D25 -> 0 | C25: =Energy!AH25 -> 0.21143123 | D25: =IFERROR((C25/B25)^(1/30)-1,"")
A27: Recycled water available (M m³/yr) | B27: =Supply!D15 -> 7.8422198 | C27: =Supply!AH15 -> 36.840097
A28: Recycled water to trees (M m³/yr) | B28: =Supply!D16 -> 0 | C28: =Supply!AH16 -> 11.052029
A29: Recycled water to agriculture (M m³/yr) | B29: =Supply!D17 -> 7.8422198 | C29: =Supply!AH17 -> 25.788068
A30: Electricity: recycled water (GWh) | B30: =Energy!D14 -> 6.2737758 | C30: =Energy!AH14 -> 23.946063
Q31: chapter 8: table 13.
B32: Note: Total demand rises over time; declining GW and GMMR are balanced by higher desalination and recycled water so total supply still matches demand.
B33: Sector water demand chart data
B34: Year | C34: Domestic | D34: Industrial | E34: Agriculture | F34: Trees
B35: 2020 | C35: =Demand!D13 -> 784.22198 | D35: =Demand!D14 -> 389.62702 | E35: =Demand!D15 -> 5865.6854 | F35: =Demand!D17 -> 0
B36: 2030 | C36: =Demand!N13 -> 885.10972 | D36: =Demand!N14 -> 551.13685 | E36: =Demand!N15 -> 6423.3676 | F36: =Demand!N17 -> 219
B37: 2040 | C37: =Demand!X13 -> 974.25822 | D37: =Demand!X14 -> 760.3065 | E37: =Demand!X15 -> 6860.0244 | F37: =Demand!X17 -> 547.5
B38: Cleaned summary charts | C38: =Demand!AH13 -> 1052.5742 | D38: =Demand!AH14 -> 1029.4841 | E38: =Demand!AH15 -> 7191.0154 | F38: =Demand!AH17 -> 547.5
B39: Total demand rises over time. Declining groundwater and GMMR are offset by desalination and treated wastewater, so total supply and total electricity demand both rise.
B59: Sector water demand full-period data
B60: Year | C60: Domestic | D60: Industrial | E60: Agriculture | F60: Trees
B61: 2020 | C61: =Demand!D13 -> 784.22198 | D61: =Demand!D14 -> 389.62702 | E61: =Demand!D15 -> 5865.6854 | F61: =Demand!D17 -> 0
B62: 2021 | C62: =Demand!E13 -> 794.86617 | D62: =Demand!E14 -> 403.93297 | E62: =Demand!E15 -> 5927.3744 | F62: =Demand!E17 -> 0
B63: 2022 | C63: =Demand!F13 -> 805.38432 | D63: =Demand!F14 -> 418.62358 | E63: =Demand!F15 -> 5987.7011 | F63: =Demand!F17 -> 0
B64: 2023 | C64: =Demand!G13 -> 815.77742 | D64: =Demand!G14 -> 433.70799 | E64: =Demand!G15 -> 6046.6831 | F64: =Demand!G17 -> 0
B65: 2024 | C65: =Demand!H13 -> 826.04645 | D65: =Demand!H14 -> 449.19554 | E65: =Demand!H15 -> 6104.3383 | F65: =Demand!H17 -> 0
B66: 2025 | C66: =Demand!I13 -> 836.1924 | D66: =Demand!I14 -> 465.0958 | E66: =Demand!I15 -> 6160.6839 | F66: =Demand!I17 -> 0
B67: 2026 | C67: =Demand!J13 -> 846.21623 | D67: =Demand!J14 -> 481.4185 | E67: =Demand!J15 -> 6215.7374 | F67: =Demand!J17 -> 0
B68: 2027 | C68: =Demand!K13 -> 856.11892 | D68: =Demand!K14 -> 498.17365 | E68: =Demand!K15 -> 6269.5157 | F68: =Demand!K17 -> 54.75
B69: 2028 | C69: =Demand!L13 -> 865.90143 | D69: =Demand!L14 -> 515.37143 | E69: =Demand!L15 -> 6322.0357 | F69: =Demand!L17 -> 109.5
B70: 2029 | C70: =Demand!M13 -> 875.56472 | D70: =Demand!M14 -> 533.02228 | E70: =Demand!M15 -> 6373.3142 | F70: =Demand!M17 -> 164.25
B71: 2030 | C71: =Demand!N13 -> 885.10972 | D71: =Demand!N14 -> 551.13685 | E71: =Demand!N15 -> 6423.3676 | F71: =Demand!N17 -> 219
B72: 2031 | C72: =Demand!O13 -> 894.53738 | D72: =Demand!O14 -> 569.72603 | E72: =Demand!O15 -> 6472.2123 | F72: =Demand!O17 -> 273.75
B73: 2032 | C73: =Demand!P13 -> 903.84864 | D73: =Demand!P14 -> 588.80096 | E73: =Demand!P15 -> 6519.8644 | F73: =Demand!P17 -> 328.5
B74: 2033 | C74: =Demand!Q13 -> 913.04442 | D74: =Demand!Q14 -> 608.373 | E74: =Demand!Q15 -> 6566.3398 | F74: =Demand!Q17 -> 383.25
B75: 2034 | C75: =Demand!R13 -> 922.12565 | D75: =Demand!R14 -> 628.4538 | E75: =Demand!R15 -> 6611.6543 | F75: =Demand!R17 -> 438
B76: 2035 | C76: =Demand!S13 -> 931.09324 | D76: =Demand!S14 -> 649.05523 | E76: =Demand!S15 -> 6655.8235 | F76: =Demand!S17 -> 492.75
B77: 2036 | C77: =Demand!T13 -> 939.9481 | D77: =Demand!T14 -> 670.18945 | E77: =Demand!T15 -> 6698.8629 | F77: =Demand!T17 -> 547.5
B78: 2037 | C78: =Demand!U13 -> 948.69113 | D78: =Demand!U14 -> 691.86886 | E78: =Demand!U15 -> 6740.7877 | F78: =Demand!U17 -> 547.5
B79: 2038 | C79: =Demand!V13 -> 957.32324 | D79: =Demand!V14 -> 714.10614 | E79: =Demand!V15 -> 6781.613 | F79: =Demand!V17 -> 547.5
B80: 2039 | C80: =Demand!W13 -> 965.8453 | D80: =Demand!W14 -> 736.91428 | E80: =Demand!W15 -> 6821.3536 | F80: =Demand!W17 -> 547.5
B81: 2040 | C81: =Demand!X13 -> 974.25822 | D81: =Demand!X14 -> 760.3065 | E81: =Demand!X15 -> 6860.0244 | F81: =Demand!X17 -> 547.5
B82: 2041 | C82: =Demand!Y13 -> 982.56286 | D82: =Demand!Y14 -> 784.29636 | E82: =Demand!Y15 -> 6897.6399 | F82: =Demand!Y17 -> 547.5
B83: 2042 | C83: =Demand!Z13 -> 990.76009 | D83: =Demand!Z14 -> 808.89768 | E83: =Demand!Z15 -> 6934.2145 | F83: =Demand!Z17 -> 547.5
B84: 2043 | C84: =Demand!AA13 -> 998.85079 | D84: =Demand!AA14 -> 834.1246 | E84: =Demand!AA15 -> 6969.7624 | F84: =Demand!AA17 -> 547.5
B85: 2044 | C85: =Demand!AB13 -> 1006.8358 | D85: =Demand!AB14 -> 859.99157 | E85: =Demand!AB15 -> 7004.2978 | F85: =Demand!AB17 -> 547.5
B86: 2045 | C86: =Demand!AC13 -> 1014.716 | D86: =Demand!AC14 -> 886.51336 | E86: =Demand!AC15 -> 7037.8346 | F86: =Demand!AC17 -> 547.5
B87: 2046 | C87: =Demand!AD13 -> 1022.4922 | D87: =Demand!AD14 -> 913.70504 | E87: =Demand!AD15 -> 7070.3865 | F87: =Demand!AD17 -> 547.5
B88: 2047 | C88: =Demand!AE13 -> 1030.1653 | D88: =Demand!AE14 -> 941.58203 | E88: =Demand!AE15 -> 7101.9671 | F88: =Demand!AE17 -> 547.5
B89: 2048 | C89: =Demand!AF13 -> 1037.7361 | D89: =Demand!AF14 -> 970.16008 | E89: =Demand!AF15 -> 7132.59 | F89: =Demand!AF17 -> 547.5
B90: 2049 | C90: =Demand!AG13 -> 1045.2055 | D90: =Demand!AG14 -> 999.45527 | E90: =Demand!AG15 -> 7162.2683 | F90: =Demand!AG17 -> 547.5
B91: 2050 | C91: =Demand!AH13 -> 1052.5742 | D91: =Demand!AH14 -> 1029.4841 | E91: =Demand!AH15 -> 7191.0154 | F91: =Demand!AH17 -> 547.5
J120: Energy demand data
B121: Year | C121: Groundwater | D121: GMMR | E121: Desalination | F121: Treated wastewater | G121: Surface water | H121: Scenario | J121: Year | K121: Groundwater | L121: GMMR | M121: Desalination | N121: Treated wastewater | O121: Total | P121: Surface water
B122: 2020 | C122: =Supply!D46+Supply!D49+Supply!D52+Supply!D65 -> 6059.6922 | D122: =Supply!D47+Supply!D50+Supply!D53 -> 912 | E122: =Supply!D57 -> 0 | F122: =Supply!D59 -> 7.8422198 | G122: =Supply!D11 -> 60 | H122: Conditional | J122: 2020 | K122: =Energy!D9 -> 2120.8923 | L122: =Energy!D10 -> 1641.6 | M122: =Energy!D11 -> 0 | N122: =Energy!D14 -> 6.2737758 | O122: =Energy!D15 -> 3780.766 | P122: =Energy!D8 -> 12
B123: 2021 | C123: =Supply!E46+Supply!E49+Supply!E52+Supply!E65 -> 6156.0564 | D123: =Supply!E47+Supply!E50+Supply!E53 -> 893.76 | E123: =Supply!E57 -> 0 | F123: =Supply!E59 -> 16.957145 | G123: =Supply!E11 -> 59.4 | H123: Conditional | J123: 2021 | K123: =Energy!E9 -> 2189.904 | L123: =Energy!E10 -> 1624.8557 | M123: =Energy!E11 -> 0 | N123: =Energy!E14 -> 6.8457849 | O123: =Energy!E15 -> 3833.4855 | P123: =Energy!E8 -> 11.88
B124: 2022 | C124: =Supply!F46+Supply!F49+Supply!F52+Supply!F65 -> 6250.709 | D124: =Supply!F47+Supply!F50+Supply!F53 -> 875.8848 | E124: =Supply!F57 -> 0 | F124: =Supply!F59 -> 26.309221 | G124: =Supply!F11 -> 58.806 | H124: Conditional | J124: 2022 | K124: =Energy!F9 -> 2259.9713 | L124: =Energy!F10 -> 1608.2822 | M124: =Energy!F11 -> 0 | N124: =Energy!F14 -> 7.4229589 | O124: =Energy!F15 -> 3887.4376 | P124: =Energy!F8 -> 11.7612
B125: 2023 | C125: =Supply!G46+Supply!G49+Supply!G52+Supply!G65 -> 6343.6893 | D125: =Supply!G47+Supply!G50+Supply!G53 -> 858.3671 | E125: =Supply!G57 -> 0 | F125: =Supply!G59 -> 35.894206 | G125: =Supply!G11 -> 58.21794 | H125: Conditional | J125: 2023 | K125: =Energy!G9 -> 2331.1153 | L125: =Energy!G10 -> 1591.8777 | M125: =Energy!G11 -> 0 | N125: =Energy!G14 -> 8.0048159 | O125: =Energy!G15 -> 3942.6414 | P125: =Energy!G8 -> 11.643588
B126: 2024 | C126: =Supply!H46+Supply!H49+Supply!H52+Supply!H65 -> 6435.0368 | D126: =Supply!H47+Supply!H50+Supply!H53 -> 841.19976 | E126: =Supply!H57 -> 0 | F126: =Supply!H59 -> 45.707904 | G126: =Supply!H11 -> 57.635761 | H126: Conditional | J126: 2024 | K126: =Energy!H9 -> 2403.3578 | L126: =Energy!H10 -> 1575.6405 | M126: =Energy!H11 -> 0 | N126: =Energy!H14 -> 8.5908831 | O126: =Energy!H15 -> 3999.1163 | P126: =Energy!H8 -> 11.527152
B127: 2025 | C127: =Supply!I46+Supply!I49+Supply!I52+Supply!I65 -> 6524.7908 | D127: =Supply!I47+Supply!I50+Supply!I53 -> 824.37577 | E127: =Supply!I57 -> 0 | F127: =Supply!I59 -> 55.74616 | G127: =Supply!I11 -> 57.059403 | H127: Conditional | J127: 2025 | K127: =Energy!I9 -> 2476.721 | L127: =Energy!I10 -> 1559.569 | M127: =Energy!I11 -> 0 | N127: =Energy!I14 -> 9.1806957 | O127: =Energy!I15 -> 4056.8825 | P127: =Energy!I8 -> 11.411881
B128: 2026 | C128: =Supply!J46+Supply!J49+Supply!J52+Supply!J65 -> 6612.9902 | D128: =Supply!J47+Supply!J50+Supply!J53 -> 807.88825 | E128: =Supply!J57 -> 0 | F128: =Supply!J59 -> 66.004866 | G128: =Supply!J11 -> 56.488809 | H128: Conditional | J128: 2026 | K128: =Energy!J9 -> 2551.228 | L128: =Energy!J10 -> 1543.6614 | M128: =Energy!J11 -> 0 | N128: =Energy!J14 -> 9.7737975 | O128: =Energy!J15 -> 4115.9609 | P128: =Energy!J8 -> 11.297762
B129: 2027 | C129: =Supply!K46+Supply!K49+Supply!K52+Supply!K65 -> 6739.6984 | D129: =Supply!K47+Supply!K50+Supply!K53 -> 791.73049 | E129: =Supply!K57 -> 14.725489 | F129: =Supply!K59 -> 76.479957 | G129: =Supply!K11 -> 55.923921 | H129: Conditional | J129: 2027 | K129: =Energy!K9 -> 2629.2895 | L129: =Energy!K10 -> 1527.916 | M129: =Energy!K11 -> 164.44681 | N129: =Energy!K14 -> 10.36974 | O129: =Energy!K15 -> 4343.2069 | P129: =Energy!K8 -> 11.184784
B130: 2028 | C130: =Supply!L46+Supply!L49+Supply!L52+Supply!L65 -> 6830.7888 | D130: =Supply!L47+Supply!L50+Supply!L53 -> 775.89588 | E130: =Supply!L57 -> 63.59183 | F130: =Supply!L59 -> 87.167411 | G130: =Supply!L11 -> 55.364682 | H130: Conditional | J130: 2028 | K130: =Energy!L9 -> 2706.3104 | L130: =Energy!L10 -> 1512.3313 | M130: =Energy!L11 -> 346.94794 | N130: =Energy!L14 -> 10.968085 | O130: =Energy!L15 -> 4587.6307 | P130: =Energy!L8 -> 11.072936
B131: 2029 | C131: =Supply!M46+Supply!M49+Supply!M52+Supply!M65 -> 6920.6225 | D131: =Supply!M47+Supply!M50+Supply!M53 -> 760.37796 | E131: =Supply!M57 -> 112.27648 | F131: =Supply!M59 -> 98.063248 | G131: =Supply!M11 -> 54.811035 | H131: Conditional | J131: 2029 | K131: =Energy!M9 -> 2784.5503 | L131: =Energy!M10 -> 1496.9055 | M131: =Energy!M11 -> 527.65231 | N131: =Energy!M14 -> 11.568399 | O131: =Energy!M15 -> 4831.6387 | P131: =Energy!M8 -> 10.962207
B132: 2030 | C132: =Supply!N46+Supply!N49+Supply!N52+Supply!N65 -> 7009.2379 | D132: =Supply!N47+Supply!N50+Supply!N53 -> 745.1704 | E132: =Supply!N57 -> 160.77945 | F132: =Supply!N59 -> 109.16353 | G132: =Supply!N11 -> 54.262925 | H132: Conditional | J132: 2030 | K132: =Energy!N9 -> 2864.0348 | L132: =Energy!N10 -> 1481.6371 | M132: =Energy!N11 -> 706.56098 | N132: =Energy!N14 -> 12.170259 | O132: =Energy!N15 -> 5075.2557 | P132: =Energy!N8 -> 10.852585
B133: 2031 | C133: =Supply!O46+Supply!O49+Supply!O52+Supply!O65 -> 7096.6733 | D133: =Supply!O47+Supply!O50+Supply!O53 -> 730.26699 | E133: =Supply!O57 -> 209.10079 | F133: =Supply!O59 -> 120.46437 | G133: =Supply!O11 -> 53.720295 | H133: Conditional | J133: 2031 | K133: =Energy!O9 -> 2944.7904 | L133: =Energy!O10 -> 1466.5244 | M133: =Energy!O11 -> 883.675 | N133: =Energy!O14 -> 12.773248 | O133: =Energy!O15 -> 5318.5071 | P133: =Energy!O8 -> 10.744059
B134: 2032 | C134: =Supply!P46+Supply!P49+Supply!P52+Supply!P65 -> 7182.9667 | D134: =Supply!P47+Supply!P50+Supply!P53 -> 715.66165 | E134: =Supply!P57 -> 257.24057 | F134: =Supply!P59 -> 131.9619 | G134: =Supply!P11 -> 53.183092 | H134: Conditional | J134: 2032 | K134: =Energy!P9 -> 3026.8444 | L134: =Energy!P10 -> 1451.5658 | M134: =Energy!P11 -> 1058.9953 | N134: =Energy!P14 -> 13.37696 | O134: =Energy!P15 -> 5561.4191 | P134: =Energy!P8 -> 10.636618
B135: 2033 | C135: =Supply!Q46+Supply!Q49+Supply!Q52+Supply!Q65 -> 7268.1563 | D135: =Supply!Q47+Supply!Q50+Supply!Q53 -> 701.34842 | E135: =Supply!Q57 -> 305.19891 | F135: =Supply!Q59 -> 143.65232 | G135: =Supply!Q11 -> 52.651261 | H135: Conditional | J135: 2033 | K135: =Energy!Q9 -> 3110.2249 | L135: =Energy!Q10 -> 1436.7599 | M135: =Energy!Q11 -> 1232.5229 | N135: =Energy!Q14 -> 13.980993 | O135: =Energy!Q15 -> 5804.0188 | P135: =Energy!Q8 -> 10.530252
B136: 2034 | C136: =Supply!R46+Supply!R49+Supply!R52+Supply!R65 -> 7352.2798 | D136: =Supply!R47+Supply!R50+Supply!R53 -> 687.32145 | E136: =Supply!R57 -> 352.97592 | F136: =Supply!R59 -> 155.53186 | G136: =Supply!R11 -> 52.124749 | H136: Conditional | J136: 2034 | K136: =Energy!R9 -> 3194.9608 | L136: =Energy!R10 -> 1422.1049 | M136: =Energy!R11 -> 1404.2585 | N136: =Energy!R14 -> 14.584954 | O136: =Energy!R15 -> 6046.3341 | P136: =Energy!R8 -> 10.42495
B137: 2035 | C137: =Supply!S46+Supply!S49+Supply!S52+Supply!S65 -> 7435.3749 | D137: =Supply!S47+Supply!S50+Supply!S53 -> 673.57502 | E137: =Supply!S57 -> 400.57177 | F137: =Supply!S59 -> 167.59678 | G137: =Supply!S11 -> 51.603501 | H137: Conditional | J137: 2035 | K137: =Energy!S9 -> 3281.0819 | L137: =Energy!S10 -> 1407.5994 | M137: =Energy!S11 -> 1574.203 | N137: =Energy!S14 -> 15.188458 | O137: =Energy!S15 -> 6288.3935 | P137: =Energy!S8 -> 10.3207
B138: 2036 | C138: =Supply!T46+Supply!T49+Supply!T52+Supply!T65 -> 7517.4794 | D138: =Supply!T47+Supply!T50+Supply!T53 -> 660.10352 | E138: =Supply!T57 -> 447.98665 | F138: =Supply!T59 -> 179.8434 | G138: =Supply!T11 -> 51.087466 | H138: Conditional | J138: 2036 | K138: =Energy!T9 -> 3368.6191 | L138: =Energy!T10 -> 1393.2419 | M138: =Energy!T11 -> 1742.3572 | N138: =Energy!T14 -> 15.791128 | O138: =Energy!T15 -> 6530.2268 | P138: =Energy!T8 -> 10.217493
B139: 2037 | C139: =Supply!U46+Supply!U49+Supply!U52+Supply!U65 -> 7598.6308 | D139: =Supply!U47+Supply!U50+Supply!U53 -> 646.90145 | E139: =Supply!U57 -> 440.47077 | F139: =Supply!U59 -> 192.26807 | G139: =Supply!U11 -> 50.576592 | H139: Conditional | J139: 2037 | K139: =Energy!U9 -> 3457.604 | L139: =Energy!U10 -> 1379.0309 | M139: =Energy!U11 -> 1732.6093 | N139: =Energy!U14 -> 16.392592 | O139: =Energy!U15 -> 6595.7521 | P139: =Energy!U8 -> 10.115318
B140: 2038 | C140: =Supply!V46+Supply!V49+Supply!V52+Supply!V65 -> 7678.8666 | D140: =Supply!V47+Supply!V50+Supply!V53 -> 633.96342 | E140: =Supply!V57 -> 432.77438 | F140: =Supply!V59 -> 204.86717 | G140: =Supply!V11 -> 50.070826 | H140: Conditional | J140: 2038 | K140: =Energy!V9 -> 3548.0694 | L140: =Energy!V10 -> 1364.9647 | M140: =Energy!V11 -> 1722.8974 | N140: =Energy!V14 -> 16.992487 | O140: =Energy!V15 -> 6662.9381 | P140: =Energy!V8 -> 10.014165
B141: 2039 | C141: =Supply!W46+Supply!W49+Supply!W52+Supply!W65 -> 7758.2241 | D141: =Supply!W47+Supply!W50+Supply!W53 -> 621.28415 | E141: =Supply!W57 -> 424.89774 | F141: =Supply!W59 -> 217.63714 | G141: =Supply!W11 -> 49.570117 | H141: Conditional | J141: 2039 | K141: =Energy!W9 -> 3640.0489 | L141: =Energy!W10 -> 1351.0421 | M141: =Energy!W11 -> 1713.2221 | N141: =Energy!W14 -> 17.590458 | O141: =Energy!W15 -> 6731.8176 | P141: =Energy!W8 -> 9.9140235
B142: 2040 | C142: =Supply!X46+Supply!X49+Supply!X52+Supply!X65 -> 7836.7407 | D142: =Supply!X47+Supply!X50+Supply!X53 -> 608.85847 | E142: =Supply!X57 -> 416.84115 | F142: =Supply!X59 -> 230.57444 | G142: =Supply!X11 -> 49.074416 | H142: Conditional | J142: 2040 | K142: =Energy!X9 -> 3733.5774 | L142: =Energy!X10 -> 1337.2615 | M142: =Energy!X11 -> 1703.5841 | N142: =Energy!X14 -> 18.186153 | O142: =Energy!X15 -> 6802.4239 | P142: =Energy!X8 -> 9.8148833
B143: 2041 | C143: =Supply!Y46+Supply!Y49+Supply!Y52+Supply!Y65 -> 7914.4536 | D143: =Supply!Y47+Supply!Y50+Supply!Y53 -> 596.6813 | E143: =Supply!Y57 -> 408.60491 | F143: =Supply!Y59 -> 243.67559 | G143: =Supply!Y11 -> 48.583672 | H143: Conditional | J143: 2041 | K143: =Energy!Y9 -> 3828.6907 | L143: =Energy!Y10 -> 1323.6214 | M143: =Energy!Y11 -> 1693.9838 | N143: =Energy!Y14 -> 18.779233 | O143: =Energy!Y15 -> 6874.7918 | P143: =Energy!Y8 -> 9.7167344
B144: 2042 | C144: =Supply!Z46+Supply!Z49+Supply!Z52+Supply!Z65 -> 7991.4002 | D144: =Supply!Z47+Supply!Z50+Supply!Z53 -> 584.74767 | E144: =Supply!Z57 -> 400.18939 | F144: =Supply!Z59 -> 256.93712 | G144: =Supply!Z11 -> 48.097835 | H144: Conditional | J144: 2042 | K144: =Energy!Z9 -> 3925.4258 | L144: =Energy!Z10 -> 1310.1205 | M144: =Energy!Z11 -> 1684.4217 | N144: =Energy!Z14 -> 19.36936 | O144: =Energy!Z15 -> 6948.9569 | P144: =Energy!Z8 -> 9.6195671
B145: 2043 | C145: =Supply!AA46+Supply!AA49+Supply!AA52+Supply!AA65 -> 8067.6177 | D145: =Supply!AA47+Supply!AA50+Supply!AA53 -> 573.05272 | E145: =Supply!AA57 -> 391.59493 | F145: =Supply!AA59 -> 270.35561 | G145: =Supply!AA11 -> 47.616857 | H145: Conditional | J145: 2043 | K145: =Energy!AA9 -> 4023.821 | L145: =Energy!AA10 -> 1296.7572 | M145: =Energy!AA11 -> 1674.8983 | N145: =Energy!AA14 -> 19.956206 | O145: =Energy!AA15 -> 7024.9561 | P145: =Energy!AA8 -> 9.5233714
B146: 2044 | C146: =Supply!AB46+Supply!AB49+Supply!AB52+Supply!AB65 -> 8143.1432 | D146: =Supply!AB47+Supply!AB50+Supply!AB53 -> 561.59167 | E146: =Supply!AB57 -> 382.82193 | F146: =Supply!AB59 -> 283.9277 | G146: =Supply!AB11 -> 47.140688 | H146: Conditional | J146: 2044 | K146: =Energy!AB9 -> 4123.9157 | L146: =Energy!AB10 -> 1283.5303 | M146: =Energy!AB11 -> 1665.4139 | N146: =Energy!AB14 -> 20.539451 | O146: =Energy!AB15 -> 7102.8274 | P146: =Energy!AB8 -> 9.4281377
B147: 2045 | C147: =Supply!AC46+Supply!AC49+Supply!AC52+Supply!AC65 -> 8218.014 | D147: =Supply!AC47+Supply!AC50+Supply!AC53 -> 550.35983 | E147: =Supply!AC57 -> 373.87082 | F147: =Supply!AC59 -> 297.65003 | G147: =Supply!AC11 -> 46.669282 | H147: Conditional | J147: 2045 | K147: =Energy!AC9 -> 4225.7505 | L147: =Energy!AC10 -> 1270.4383 | M147: =Energy!AC11 -> 1655.9688 | N147: =Energy!AC14 -> 21.118777 | O147: =Energy!AC15 -> 7182.6103 | P147: =Energy!AC8 -> 9.3338563
B148: 2046 | C148: =Supply!AD46+Supply!AD49+Supply!AD52+Supply!AD65 -> 8292.2672 | D148: =Supply!AD47+Supply!AD50+Supply!AD53 -> 539.35264 | E148: =Supply!AD57 -> 364.74201 | F148: =Supply!AD59 -> 311.5193 | G148: =Supply!AD11 -> 46.202589 | H148: Conditional | J148: 2046 | K148: =Energy!AD9 -> 4329.3675 | L148: =Energy!AD10 -> 1257.4798 | M148: =Energy!AD11 -> 1646.5635 | N148: =Energy!AD14 -> 21.693877 | O148: =Energy!AD15 -> 7264.3452 | P148: =Energy!AD8 -> 9.2405177
B149: 2047 | C149: =Supply!AE46+Supply!AE49+Supply!AE52+Supply!AE65 -> 8365.9401 | D149: =Supply!AE47+Supply!AE50+Supply!AE53 -> 528.56558 | E149: =Supply!AE57 -> 355.43597 | F149: =Supply!AE59 -> 325.53225 | G149: =Supply!AE11 -> 45.740563 | H149: Conditional | J149: 2047 | K149: =Energy!AE9 -> 4434.8099 | L149: =Energy!AE10 -> 1244.6535 | M149: =Energy!AE11 -> 1637.1982 | N149: =Energy!AE14 -> 22.264448 | O149: =Energy!AE15 -> 7348.0742 | P149: =Energy!AE8 -> 9.1481126
...
